[{"dis_TEMSILCILIK_ID":0,"birim_ID":0,"ilce_ID":2,"ilce_ADI":"ACIPAYAM","belde_ID":0,"il_ID":20,"il_ADI":"DENİZLİ","ulke_ID":0,"muhtarlik_ID":0,"muhtarlik_ADI":null,"cezaevi_ID":0,"sandik_NO":null,"sandik_SONUC_TUTANAGI":0,"sandik_DOKUM_CETVELI":0,"denetim_TUTANAGI":0,"bagimsiz_TOPLAM_OY":34433,"gumruk_ID":0,"sandik_RUMUZ":null,"gumruk_SANDIK_TARIHI":null,"birlestirme_TUTANAGI_KURUL":0,"birlestirme_TUTANAGI_ULKE":0,"birlestirme_TUTANAGI_ILCE":0,"birlestirme_TUTANAGI_IL":0,"birlestirme_TUTANAGI_DIS_TEMSILCILIK":0,"birlestirme_TUTANAGI_GUMRUK_ILCE":0,"birlestirme_TUTANAGI_GUMRUK_RUMUZ":0,"birlestirme_TUTANAGI_GUMRUK_KURUL":0,"birlestirme_TUTANAGI_TUMDUNYA":0,"birlestirme_TUTANAGI_ULKELER":0,"birlestirme_TUTANAGI_GUMRUKLER":0,"bagimsiz3_ALDIGI_OY":14361,"bagimsiz4_ALDIGI_OY":0,"bagimsiz5_ALDIGI_OY":0,"bagimsiz6_ALDIGI_OY":0,"bagimsiz7_ALDIGI_OY":0,"bagimsiz8_ALDIGI_OY":0,"bagimsiz9_ALDIGI_OY":0,"bagimsiz10_ALDIGI_OY":0,"bagimsiz11_ALDIGI_OY":0,"bagimsiz12_ALDIGI_OY":0,"bagimsiz13_ALDIGI_OY":0,"bagimsiz14_ALDIGI_OY":0,"bagimsiz15_ALDIGI_OY":0,"bagimsiz16_ALDIGI_OY":0,"bagimsiz17_ALDIGI_OY":0,"bagimsiz18_ALDIGI_OY":0,"bagimsiz19_ALDIGI_OY":0,"bagimsiz20_ALDIGI_OY":0,"bagimsiz21_ALDIGI_OY":0,"bagimsiz22_ALDIGI_OY":0,"bagimsiz23_ALDIGI_OY":0,"bagimsiz24_ALDIGI_OY":0,"bagimsiz25_ALDIGI_OY":0,"bagimsiz26_ALDIGI_OY":0,"bagimsiz27_ALDIGI_OY":0,"bagimsiz28_ALDIGI_OY":0,"bagimsiz29_ALDIGI_OY":0,"bagimsiz30_ALDIGI_OY":0,"bagimsiz31_ALDIGI_OY":0,"bagimsiz32_ALDIGI_OY":0,"bagimsiz33_ALDIGI_OY":0,"bagimsiz34_ALDIGI_OY":0,"bagimsiz35_ALDIGI_OY":0,"bagimsiz36_ALDIGI_OY":0,"bagimsiz37_ALDIGI_OY":0,"bagimsiz38_ALDIGI_OY":0,"bagimsiz39_ALDIGI_OY":0,"bagimsiz40_ALDIGI_OY":0,"bagimsiz41_ALDIGI_OY":0,"bagimsiz42_ALDIGI_OY":0,"bagimsiz43_ALDIGI_OY":0,"bagimsiz44_ALDIGI_OY":0,"bagimsiz45_ALDIGI_OY":0,"bagimsiz46_ALDIGI_OY":0,"bagimsiz47_ALDIGI_OY":0,"bagimsiz48_ALDIGI_OY":0,"bagimsiz49_ALDIGI_OY":0,"bagimsiz50_ALDIGI_OY":0,"ittifak1_ALDIGI_OY":0,"ittifak2_ALDIGI_OY":0,"ittifak3_ALDIGI_OY":0,"ittifak4_ALDIGI_OY":0,"ittifak5_ALDIGI_OY":0,"versiyon":2671,"son_ISLEM_TARIHI":"2014-08-10T17:03:35.000+0000","degisiklik_NEDENI":0,"sandik_SONUC_ID":0,"secim_ID":13340,"secim_TURU":0,"parti1_ALDIGI_OY":0,"parti2_ALDIGI_OY":0,"parti3_ALDIGI_OY":0,"parti4_ALDIGI_OY":0,"parti5_ALDIGI_OY":0,"parti6_ALDIGI_OY":0,"parti7_ALDIGI_OY":0,"parti8_ALDIGI_OY":0,"parti9_ALDIGI_OY":0,"parti10_ALDIGI_OY":0,"parti11_ALDIGI_OY":0,"parti12_ALDIGI_OY":0,"parti13_ALDIGI_OY":0,"parti14_ALDIGI_OY":0,"parti15_ALDIGI_OY":0,"parti16_ALDIGI_OY":0,"parti17_ALDIGI_OY":0,"parti18_ALDIGI_OY":0,"parti19_ALDIGI_OY":0,"parti20_ALDIGI_OY":0,"parti21_ALDIGI_OY":0,"parti22_ALDIGI_OY":0,"parti23_ALDIGI_OY":0,"parti24_ALDIGI_OY":0,"parti25_ALDIGI_OY":0,"parti26_ALDIGI_OY":0,"parti27_ALDIGI_OY":0,"parti28_ALDIGI_OY":0,"parti29_ALDIGI_OY":0,"parti30_ALDIGI_OY":0,"bagimsiz1_ALDIGI_OY":19361,"bagimsiz2_ALDIGI_OY":711,"sandik_ID":0,"secmen_SAYISI":42287,"oy_KULLANAN_SECMEN_SAYISI":35496,"itirazli_GECERLI_OY_SAYISI":0,"gecerli_OY_TOPLAMI":34433,"gecersiz_OY_TOPLAMI":1063,"itirazsiz_GECERLI_OY_SAYISI":34433},{"dis_TEMSILCILIK_ID":0,"birim_ID":0,"ilce_ID":662,"ilce_ADI":"BABADAĞ","belde_ID":0,"il_ID":20,"il_ADI":"DENİZLİ","ulke_ID":0,"muhtarlik_ID":0,"muhtarlik_ADI":null,"cezaevi_ID":0,"sandik_NO":null,"sandik_SONUC_TUTANAGI":0,"sandik_DOKUM_CETVELI":0,"denetim_TUTANAGI":0,"bagimsiz_TOPLAM_OY":4084,"gumruk_ID":0,"sandik_RUMUZ":null,"gumruk_SANDIK_TARIHI":null,"birlestirme_TUTANAGI_KURUL":0,"birlestirme_TUTANAGI_ULKE":0,"birlestirme_TUTANAGI_ILCE":0,"birlestirme_TUTANAGI_IL":0,"birlestirme_TUTANAGI_DIS_TEMSILCILIK":0,"birlestirme_TUTANAGI_GUMRUK_ILCE":0,"birlestirme_TUTANAGI_GUMRUK_RUMUZ":0,"birlestirme_TUTANAGI_GUMRUK_KURUL":0,"birlestirme_TUTANAGI_TUMDUNYA":0,"birlestirme_TUTANAGI_ULKELER":0,"birlestirme_TUTANAGI_GUMRUKLER":0,"bagimsiz3_ALDIGI_OY":1963,"bagimsiz4_ALDIGI_OY":0,"bagimsiz5_ALDIGI_OY":0,"bagimsiz6_ALDIGI_OY":0,"bagimsiz7_ALDIGI_OY":0,"bagimsiz8_ALDIGI_OY":0,"bagimsiz9_ALDIGI_OY":0,"bagimsiz10_ALDIGI_OY":0,"bagimsiz11_ALDIGI_OY":0,"bagimsiz12_ALDIGI_OY":0,"bagimsiz13_ALDIGI_OY":0,"bagimsiz14_ALDIGI_OY":0,"bagimsiz15_ALDIGI_OY":0,"bagimsiz16_ALDIGI_OY":0,"bagimsiz17_ALDIGI_OY":0,"bagimsiz18_ALDIGI_OY":0,"bagimsiz19_ALDIGI_OY":0,"bagimsiz20_ALDIGI_OY":0,"bagimsiz21_ALDIGI_OY":0,"bagimsiz22_ALDIGI_OY":0,"bagimsiz23_ALDIGI_OY":0,"bagimsiz24_ALDIGI_OY":0,"bagimsiz25_ALDIGI_OY":0,"bagimsiz26_ALDIGI_OY":0,"bagimsiz27_ALDIGI_OY":0,"bagimsiz28_ALDIGI_OY":0,"bagimsiz29_ALDIGI_OY":0,"bagimsiz30_ALDIGI_OY":0,"bagimsiz31_ALDIGI_OY":0,"bagimsiz32_ALDIGI_OY":0,"bagimsiz33_ALDIGI_OY":0,"bagimsiz34_ALDIGI_OY":0,"bagimsiz35_ALDIGI_OY":0,"bagimsiz36_ALDIGI_OY":0,"bagimsiz37_ALDIGI_OY":0,"bagimsiz38_ALDIGI_OY":0,"bagimsiz39_ALDIGI_OY":0,"bagimsiz40_ALDIGI_OY":0,"bagimsiz41_ALDIGI_OY":0,"bagimsiz42_ALDIGI_OY":0,"bagimsiz43_ALDIGI_OY":0,"bagimsiz44_ALDIGI_OY":0,"bagimsiz45_ALDIGI_OY":0,"bagimsiz46_ALDIGI_OY":0,"bagimsiz47_ALDIGI_OY":0,"bagimsiz48_ALDIGI_OY":0,"bagimsiz49_ALDIGI_OY":0,"bagimsiz50_ALDIGI_OY":0,"ittifak1_ALDIGI_OY":0,"ittifak2_ALDIGI_OY":0,"ittifak3_ALDIGI_OY":0,"ittifak4_ALDIGI_OY":0,"ittifak5_ALDIGI_OY":0,"versiyon":2671,"son_ISLEM_TARIHI":"2014-08-10T17:38:51.000+0000","degisiklik_NEDENI":0,"sandik_SONUC_ID":0,"secim_ID":13340,"secim_TURU":0,"parti1_ALDIGI_OY":0,"parti2_ALDIGI_OY":0,"parti3_ALDIGI_OY":0,"parti4_ALDIGI_OY":0,"parti5_ALDIGI_OY":0,"parti6_ALDIGI_OY":0,"parti7_ALDIGI_OY":0,"parti8_ALDIGI_OY":0,"parti9_ALDIGI_OY":0,"parti10_ALDIGI_OY":0,"parti11_ALDIGI_OY":0,"parti12_ALDIGI_OY":0,"parti13_ALDIGI_OY":0,"parti14_ALDIGI_OY":0,"parti15_ALDIGI_OY":0,"parti16_ALDIGI_OY":0,"parti17_ALDIGI_OY":0,"parti18_ALDIGI_OY":0,"parti19_ALDIGI_OY":0,"parti20_ALDIGI_OY":0,"parti21_ALDIGI_OY":0,"parti22_ALDIGI_OY":0,"parti23_ALDIGI_OY":0,"parti24_ALDIGI_OY":0,"parti25_ALDIGI_OY":0,"parti26_ALDIGI_OY":0,"parti27_ALDIGI_OY":0,"parti28_ALDIGI_OY":0,"parti29_ALDIGI_OY":0,"parti30_ALDIGI_OY":0,"bagimsiz1_ALDIGI_OY":2053,"bagimsiz2_ALDIGI_OY":68,"sandik_ID":0,"secmen_SAYISI":4914,"oy_KULLANAN_SECMEN_SAYISI":4194,"itirazli_GECERLI_OY_SAYISI":0,"gecerli_OY_TOPLAMI":4084,"gecersiz_OY_TOPLAMI":110,"itirazsiz_GECERLI_OY_SAYISI":4084},{"dis_TEMSILCILIK_ID":0,"birim_ID":0,"ilce_ID":774,"ilce_ADI":"BAKLAN","belde_ID":0,"il_ID":20,"il_ADI":"DENİZLİ","ulke_ID":0,"muhtarlik_ID":0,"muhtarlik_ADI":null,"cezaevi_ID":0,"sandik_NO":null,"sandik_SONUC_TUTANAGI":0,"sandik_DOKUM_CETVELI":0,"denetim_TUTANAGI":0,"bagimsiz_TOPLAM_OY":3817,"gumruk_ID":0,"sandik_RUMUZ":null,"gumruk_SANDIK_TARIHI":null,"birlestirme_TUTANAGI_KURUL":0,"birlestirme_TUTANAGI_ULKE":0,"birlestirme_TUTANAGI_ILCE":0,"birlestirme_TUTANAGI_IL":0,"birlestirme_TUTANAGI_DIS_TEMSILCILIK":0,"birlestirme_TUTANAGI_GUMRUK_ILCE":0,"birlestirme_TUTANAGI_GUMRUK_RUMUZ":0,"birlestirme_TUTANAGI_GUMRUK_KURUL":0,"birlestirme_TUTANAGI_TUMDUNYA":0,"birlestirme_TUTANAGI_ULKELER":0,"birlestirme_TUTANAGI_GUMRUKLER":0,"bagimsiz3_ALDIGI_OY":1904,"bagimsiz4_ALDIGI_OY":0,"bagimsiz5_ALDIGI_OY":0,"bagimsiz6_ALDIGI_OY":0,"bagimsiz7_ALDIGI_OY":0,"bagimsiz8_ALDIGI_OY":0,"bagimsiz9_ALDIGI_OY":0,"bagimsiz10_ALDIGI_OY":0,"bagimsiz11_ALDIGI_OY":0,"bagimsiz12_ALDIGI_OY":0,"bagimsiz13_ALDIGI_OY":0,"bagimsiz14_ALDIGI_OY":0,"bagimsiz15_ALDIGI_OY":0,"bagimsiz16_ALDIGI_OY":0,"bagimsiz17_ALDIGI_OY":0,"bagimsiz18_ALDIGI_OY":0,"bagimsiz19_ALDIGI_OY":0,"bagimsiz20_ALDIGI_OY":0,"bagimsiz21_ALDIGI_OY":0,"bagimsiz22_ALDIGI_OY":0,"bagimsiz23_ALDIGI_OY":0,"bagimsiz24_ALDIGI_OY":0,"bagimsiz25_ALDIGI_OY":0,"bagimsiz26_ALDIGI_OY":0,"bagimsiz27_ALDIGI_OY":0,"bagimsiz28_ALDIGI_OY":0,"bagimsiz29_ALDIGI_OY":0,"bagimsiz30_ALDIGI_OY":0,"bagimsiz31_ALDIGI_OY":0,"bagimsiz32_ALDIGI_OY":0,"bagimsiz33_ALDIGI_OY":0,"bagimsiz34_ALDIGI_OY":0,"bagimsiz35_ALDIGI_OY":0,"bagimsiz36_ALDIGI_OY":0,"bagimsiz37_ALDIGI_OY":0,"bagimsiz38_ALDIGI_OY":0,"bagimsiz39_ALDIGI_OY":0,"bagimsiz40_ALDIGI_OY":0,"bagimsiz41_ALDIGI_OY":0,"bagimsiz42_ALDIGI_OY":0,"bagimsiz43_ALDIGI_OY":0,"bagimsiz44_ALDIGI_OY":0,"bagimsiz45_ALDIGI_OY":0,"bagimsiz46_ALDIGI_OY":0,"bagimsiz47_ALDIGI_OY":0,"bagimsiz48_ALDIGI_OY":0,"bagimsiz49_ALDIGI_OY":0,"bagimsiz50_ALDIGI_OY":0,"ittifak1_ALDIGI_OY":0,"ittifak2_ALDIGI_OY":0,"ittifak3_ALDIGI_OY":0,"ittifak4_ALDIGI_OY":0,"ittifak5_ALDIGI_OY":0,"versiyon":2671,"son_ISLEM_TARIHI":"2014-08-10T16:48:20.000+0000","degisiklik_NEDENI":0,"sandik_SONUC_ID":0,"secim_ID":13340,"secim_TURU":0,"parti1_ALDIGI_OY":0,"parti2_ALDIGI_OY":0,"parti3_ALDIGI_OY":0,"parti4_ALDIGI_OY":0,"parti5_ALDIGI_OY":0,"parti6_ALDIGI_OY":0,"parti7_ALDIGI_OY":0,"parti8_ALDIGI_OY":0,"parti9_ALDIGI_OY":0,"parti10_ALDIGI_OY":0,"parti11_ALDIGI_OY":0,"parti12_ALDIGI_OY":0,"parti13_ALDIGI_OY":0,"parti14_ALDIGI_OY":0,"parti15_ALDIGI_OY":0,"parti16_ALDIGI_OY":0,"parti17_ALDIGI_OY":0,"parti18_ALDIGI_OY":0,"parti19_ALDIGI_OY":0,"parti20_ALDIGI_OY":0,"parti21_ALDIGI_OY":0,"parti22_ALDIGI_OY":0,"parti23_ALDIGI_OY":0,"parti24_ALDIGI_OY":0,"parti25_ALDIGI_OY":0,"parti26_ALDIGI_OY":0,"parti27_ALDIGI_OY":0,"parti28_ALDIGI_OY":0,"parti29_ALDIGI_OY":0,"parti30_ALDIGI_OY":0,"bagimsiz1_ALDIGI_OY":1827,"bagimsiz2_ALDIGI_OY":86,"sandik_ID":0,"secmen_SAYISI":4605,"oy_KULLANAN_SECMEN_SAYISI":3938,"itirazli_GECERLI_OY_SAYISI":0,"gecerli_OY_TOPLAMI":3817,"gecersiz_OY_TOPLAMI":121,"itirazsiz_GECERLI_OY_SAYISI":3817},{"dis_TEMSILCILIK_ID":0,"birim_ID":0,"ilce_ID":667,"ilce_ADI":"BEKİLLİ","belde_ID":0,"il_ID":20,"il_ADI":"DENİZLİ","ulke_ID":0,"muhtarlik_ID":0,"muhtarlik_ADI":null,"cezaevi_ID":0,"sandik_NO":null,"sandik_SONUC_TUTANAGI":0,"sandik_DOKUM_CETVELI":0,"denetim_TUTANAGI":0,"bagimsiz_TOPLAM_OY":5011,"gumruk_ID":0,"sandik_RUMUZ":null,"gumruk_SANDIK_TARIHI":null,"birlestirme_TUTANAGI_KURUL":0,"birlestirme_TUTANAGI_ULKE":0,"birlestirme_TUTANAGI_ILCE":0,"birlestirme_TUTANAGI_IL":0,"birlestirme_TUTANAGI_DIS_TEMSILCILIK":0,"birlestirme_TUTANAGI_GUMRUK_ILCE":0,"birlestirme_TUTANAGI_GUMRUK_RUMUZ":0,"birlestirme_TUTANAGI_GUMRUK_KURUL":0,"birlestirme_TUTANAGI_TUMDUNYA":0,"birlestirme_TUTANAGI_ULKELER":0,"birlestirme_TUTANAGI_GUMRUKLER":0,"bagimsiz3_ALDIGI_OY":3002,"bagimsiz4_ALDIGI_OY":0,"bagimsiz5_ALDIGI_OY":0,"bagimsiz6_ALDIGI_OY":0,"bagimsiz7_ALDIGI_OY":0,"bagimsiz8_ALDIGI_OY":0,"bagimsiz9_ALDIGI_OY":0,"bagimsiz10_ALDIGI_OY":0,"bagimsiz11_ALDIGI_OY":0,"bagimsiz12_ALDIGI_OY":0,"bagimsiz13_ALDIGI_OY":0,"bagimsiz14_ALDIGI_OY":0,"bagimsiz15_ALDIGI_OY":0,"bagimsiz16_ALDIGI_OY":0,"bagimsiz17_ALDIGI_OY":0,"bagimsiz18_ALDIGI_OY":0,"bagimsiz19_ALDIGI_OY":0,"bagimsiz20_ALDIGI_OY":0,"bagimsiz21_ALDIGI_OY":0,"bagimsiz22_ALDIGI_OY":0,"bagimsiz23_ALDIGI_OY":0,"bagimsiz24_ALDIGI_OY":0,"bagimsiz25_ALDIGI_OY":0,"bagimsiz26_ALDIGI_OY":0,"bagimsiz27_ALDIGI_OY":0,"bagimsiz28_ALDIGI_OY":0,"bagimsiz29_ALDIGI_OY":0,"bagimsiz30_ALDIGI_OY":0,"bagimsiz31_ALDIGI_OY":0,"bagimsiz32_ALDIGI_OY":0,"bagimsiz33_ALDIGI_OY":0,"bagimsiz34_ALDIGI_OY":0,"bagimsiz35_ALDIGI_OY":0,"bagimsiz36_ALDIGI_OY":0,"bagimsiz37_ALDIGI_OY":0,"bagimsiz38_ALDIGI_OY":0,"bagimsiz39_ALDIGI_OY":0,"bagimsiz40_ALDIGI_OY":0,"bagimsiz41_ALDIGI_OY":0,"bagimsiz42_ALDIGI_OY":0,"bagimsiz43_ALDIGI_OY":0,"bagimsiz44_ALDIGI_OY":0,"bagimsiz45_ALDIGI_OY":0,"bagimsiz46_ALDIGI_OY":0,"bagimsiz47_ALDIGI_OY":0,"bagimsiz48_ALDIGI_OY":0,"bagimsiz49_ALDIGI_OY":0,"bagimsiz50_ALDIGI_OY":0,"ittifak1_ALDIGI_OY":0,"ittifak2_ALDIGI_OY":0,"ittifak3_ALDIGI_OY":0,"ittifak4_ALDIGI_OY":0,"ittifak5_ALDIGI_OY":0,"versiyon":2671,"son_ISLEM_TARIHI":"2014-08-10T16:42:40.000+0000","degisiklik_NEDENI":0,"sandik_SONUC_ID":0,"secim_ID":13340,"secim_TURU":0,"parti1_ALDIGI_OY":0,"parti2_ALDIGI_OY":0,"parti3_ALDIGI_OY":0,"parti4_ALDIGI_OY":0,"parti5_ALDIGI_OY":0,"parti6_ALDIGI_OY":0,"parti7_ALDIGI_OY":0,"parti8_ALDIGI_OY":0,"parti9_ALDIGI_OY":0,"parti10_ALDIGI_OY":0,"parti11_ALDIGI_OY":0,"parti12_ALDIGI_OY":0,"parti13_ALDIGI_OY":0,"parti14_ALDIGI_OY":0,"parti15_ALDIGI_OY":0,"parti16_ALDIGI_OY":0,"parti17_ALDIGI_OY":0,"parti18_ALDIGI_OY":0,"parti19_ALDIGI_OY":0,"parti20_ALDIGI_OY":0,"parti21_ALDIGI_OY":0,"parti22_ALDIGI_OY":0,"parti23_ALDIGI_OY":0,"parti24_ALDIGI_OY":0,"parti25_ALDIGI_OY":0,"parti26_ALDIGI_OY":0,"parti27_ALDIGI_OY":0,"parti28_ALDIGI_OY":0,"parti29_ALDIGI_OY":0,"parti30_ALDIGI_OY":0,"bagimsiz1_ALDIGI_OY":1914,"bagimsiz2_ALDIGI_OY":95,"sandik_ID":0,"secmen_SAYISI":6153,"oy_KULLANAN_SECMEN_SAYISI":5153,"itirazli_GECERLI_OY_SAYISI":0,"gecerli_OY_TOPLAMI":5011,"gecersiz_OY_TOPLAMI":142,"itirazsiz_GECERLI_OY_SAYISI":5011},{"dis_TEMSILCILIK_ID":0,"birim_ID":0,"ilce_ID":781,"ilce_ADI":"BEYAĞAÇ","belde_ID":0,"il_ID":20,"il_ADI":"DENİZLİ","ulke_ID":0,"muhtarlik_ID":0,"muhtarlik_ADI":null,"cezaevi_ID":0,"sandik_NO":null,"sandik_SONUC_TUTANAGI":0,"sandik_DOKUM_CETVELI":0,"denetim_TUTANAGI":0,"bagimsiz_TOPLAM_OY":4367,"gumruk_ID":0,"sandik_RUMUZ":null,"gumruk_SANDIK_TARIHI":null,"birlestirme_TUTANAGI_KURUL":0,"birlestirme_TUTANAGI_ULKE":0,"birlestirme_TUTANAGI_ILCE":0,"birlestirme_TUTANAGI_IL":0,"birlestirme_TUTANAGI_DIS_TEMSILCILIK":0,"birlestirme_TUTANAGI_GUMRUK_ILCE":0,"birlestirme_TUTANAGI_GUMRUK_RUMUZ":0,"birlestirme_TUTANAGI_GUMRUK_KURUL":0,"birlestirme_TUTANAGI_TUMDUNYA":0,"birlestirme_TUTANAGI_ULKELER":0,"birlestirme_TUTANAGI_GUMRUKLER":0,"bagimsiz3_ALDIGI_OY":1822,"bagimsiz4_ALDIGI_OY":0,"bagimsiz5_ALDIGI_OY":0,"bagimsiz6_ALDIGI_OY":0,"bagimsiz7_ALDIGI_OY":0,"bagimsiz8_ALDIGI_OY":0,"bagimsiz9_ALDIGI_OY":0,"bagimsiz10_ALDIGI_OY":0,"bagimsiz11_ALDIGI_OY":0,"bagimsiz12_ALDIGI_OY":0,"bagimsiz13_ALDIGI_OY":0,"bagimsiz14_ALDIGI_OY":0,"bagimsiz15_ALDIGI_OY":0,"bagimsiz16_ALDIGI_OY":0,"bagimsiz17_ALDIGI_OY":0,"bagimsiz18_ALDIGI_OY":0,"bagimsiz19_ALDIGI_OY":0,"bagimsiz20_ALDIGI_OY":0,"bagimsiz21_ALDIGI_OY":0,"bagimsiz22_ALDIGI_OY":0,"bagimsiz23_ALDIGI_OY":0,"bagimsiz24_ALDIGI_OY":0,"bagimsiz25_ALDIGI_OY":0,"bagimsiz26_ALDIGI_OY":0,"bagimsiz27_ALDIGI_OY":0,"bagimsiz28_ALDIGI_OY":0,"bagimsiz29_ALDIGI_OY":0,"bagimsiz30_ALDIGI_OY":0,"bagimsiz31_ALDIGI_OY":0,"bagimsiz32_ALDIGI_OY":0,"bagimsiz33_ALDIGI_OY":0,"bagimsiz34_ALDIGI_OY":0,"bagimsiz35_ALDIGI_OY":0,"bagimsiz36_ALDIGI_OY":0,"bagimsiz37_ALDIGI_OY":0,"bagimsiz38_ALDIGI_OY":0,"bagimsiz39_ALDIGI_OY":0,"bagimsiz40_ALDIGI_OY":0,"bagimsiz41_ALDIGI_OY":0,"bagimsiz42_ALDIGI_OY":0,"bagimsiz43_ALDIGI_OY":0,"bagimsiz44_ALDIGI_OY":0,"bagimsiz45_ALDIGI_OY":0,"bagimsiz46_ALDIGI_OY":0,"bagimsiz47_ALDIGI_OY":0,"bagimsiz48_ALDIGI_OY":0,"bagimsiz49_ALDIGI_OY":0,"bagimsiz50_ALDIGI_OY":0,"ittifak1_ALDIGI_OY":0,"ittifak2_ALDIGI_OY":0,"ittifak3_ALDIGI_OY":0,"ittifak4_ALDIGI_OY":0,"ittifak5_ALDIGI_OY":0,"versiyon":2671,"son_ISLEM_TARIHI":"2014-08-10T17:37:29.000+0000","degisiklik_NEDENI":0,"sandik_SONUC_ID":0,"secim_ID":13340,"secim_TURU":0,"parti1_ALDIGI_OY":0,"parti2_ALDIGI_OY":0,"parti3_ALDIGI_OY":0,"parti4_ALDIGI_OY":0,"parti5_ALDIGI_OY":0,"parti6_ALDIGI_OY":0,"parti7_ALDIGI_OY":0,"parti8_ALDIGI_OY":0,"parti9_ALDIGI_OY":0,"parti10_ALDIGI_OY":0,"parti11_ALDIGI_OY":0,"parti12_ALDIGI_OY":0,"parti13_ALDIGI_OY":0,"parti14_ALDIGI_OY":0,"parti15_ALDIGI_OY":0,"parti16_ALDIGI_OY":0,"parti17_ALDIGI_OY":0,"parti18_ALDIGI_OY":0,"parti19_ALDIGI_OY":0,"parti20_ALDIGI_OY":0,"parti21_ALDIGI_OY":0,"parti22_ALDIGI_OY":0,"parti23_ALDIGI_OY":0,"parti24_ALDIGI_OY":0,"parti25_ALDIGI_OY":0,"parti26_ALDIGI_OY":0,"parti27_ALDIGI_OY":0,"parti28_ALDIGI_OY":0,"parti29_ALDIGI_OY":0,"parti30_ALDIGI_OY":0,"bagimsiz1_ALDIGI_OY":2425,"bagimsiz2_ALDIGI_OY":120,"sandik_ID":0,"secmen_SAYISI":5435,"oy_KULLANAN_SECMEN_SAYISI":4508,"itirazli_GECERLI_OY_SAYISI":0,"gecerli_OY_TOPLAMI":4367,"gecersiz_OY_TOPLAMI":141,"itirazsiz_GECERLI_OY_SAYISI":4367},{"dis_TEMSILCILIK_ID":0,"birim_ID":0,"ilce_ID":782,"ilce_ADI":"BOZKURT","belde_ID":0,"il_ID":20,"il_ADI":"DENİZLİ","ulke_ID":0,"muhtarlik_ID":0,"muhtarlik_ADI":null,"cezaevi_ID":0,"sandik_NO":null,"sandik_SONUC_TUTANAGI":0,"sandik_DOKUM_CETVELI":0,"denetim_TUTANAGI":0,"bagimsiz_TOPLAM_OY":7341,"gumruk_ID":0,"sandik_RUMUZ":null,"gumruk_SANDIK_TARIHI":null,"birlestirme_TUTANAGI_KURUL":0,"birlestirme_TUTANAGI_ULKE":0,"birlestirme_TUTANAGI_ILCE":0,"birlestirme_TUTANAGI_IL":0,"birlestirme_TUTANAGI_DIS_TEMSILCILIK":0,"birlestirme_TUTANAGI_GUMRUK_ILCE":0,"birlestirme_TUTANAGI_GUMRUK_RUMUZ":0,"birlestirme_TUTANAGI_GUMRUK_KURUL":0,"birlestirme_TUTANAGI_TUMDUNYA":0,"birlestirme_TUTANAGI_ULKELER":0,"birlestirme_TUTANAGI_GUMRUKLER":0,"bagimsiz3_ALDIGI_OY":4177,"bagimsiz4_ALDIGI_OY":0,"bagimsiz5_ALDIGI_OY":0,"bagimsiz6_ALDIGI_OY":0,"bagimsiz7_ALDIGI_OY":0,"bagimsiz8_ALDIGI_OY":0,"bagimsiz9_ALDIGI_OY":0,"bagimsiz10_ALDIGI_OY":0,"bagimsiz11_ALDIGI_OY":0,"bagimsiz12_ALDIGI_OY":0,"bagimsiz13_ALDIGI_OY":0,"bagimsiz14_ALDIGI_OY":0,"bagimsiz15_ALDIGI_OY":0,"bagimsiz16_ALDIGI_OY":0,"bagimsiz17_ALDIGI_OY":0,"bagimsiz18_ALDIGI_OY":0,"bagimsiz19_ALDIGI_OY":0,"bagimsiz20_ALDIGI_OY":0,"bagimsiz21_ALDIGI_OY":0,"bagimsiz22_ALDIGI_OY":0,"bagimsiz23_ALDIGI_OY":0,"bagimsiz24_ALDIGI_OY":0,"bagimsiz25_ALDIGI_OY":0,"bagimsiz26_ALDIGI_OY":0,"bagimsiz27_ALDIGI_OY":0,"bagimsiz28_ALDIGI_OY":0,"bagimsiz29_ALDIGI_OY":0,"bagimsiz30_ALDIGI_OY":0,"bagimsiz31_ALDIGI_OY":0,"bagimsiz32_ALDIGI_OY":0,"bagimsiz33_ALDIGI_OY":0,"bagimsiz34_ALDIGI_OY":0,"bagimsiz35_ALDIGI_OY":0,"bagimsiz36_ALDIGI_OY":0,"bagimsiz37_ALDIGI_OY":0,"bagimsiz38_ALDIGI_OY":0,"bagimsiz39_ALDIGI_OY":0,"bagimsiz40_ALDIGI_OY":0,"bagimsiz41_ALDIGI_OY":0,"bagimsiz42_ALDIGI_OY":0,"bagimsiz43_ALDIGI_OY":0,"bagimsiz44_ALDIGI_OY":0,"bagimsiz45_ALDIGI_OY":0,"bagimsiz46_ALDIGI_OY":0,"bagimsiz47_ALDIGI_OY":0,"bagimsiz48_ALDIGI_OY":0,"bagimsiz49_ALDIGI_OY":0,"bagimsiz50_ALDIGI_OY":0,"ittifak1_ALDIGI_OY":0,"ittifak2_ALDIGI_OY":0,"ittifak3_ALDIGI_OY":0,"ittifak4_ALDIGI_OY":0,"ittifak5_ALDIGI_OY":0,"versiyon":2671,"son_ISLEM_TARIHI":"2014-08-10T16:30:40.000+0000","degisiklik_NEDENI":0,"sandik_SONUC_ID":0,"secim_ID":13340,"secim_TURU":0,"parti1_ALDIGI_OY":0,"parti2_ALDIGI_OY":0,"parti3_ALDIGI_OY":0,"parti4_ALDIGI_OY":0,"parti5_ALDIGI_OY":0,"parti6_ALDIGI_OY":0,"parti7_ALDIGI_OY":0,"parti8_ALDIGI_OY":0,"parti9_ALDIGI_OY":0,"parti10_ALDIGI_OY":0,"parti11_ALDIGI_OY":0,"parti12_ALDIGI_OY":0,"parti13_ALDIGI_OY":0,"parti14_ALDIGI_OY":0,"parti15_ALDIGI_OY":0,"parti16_ALDIGI_OY":0,"parti17_ALDIGI_OY":0,"parti18_ALDIGI_OY":0,"parti19_ALDIGI_OY":0,"parti20_ALDIGI_OY":0,"parti21_ALDIGI_OY":0,"parti22_ALDIGI_OY":0,"parti23_ALDIGI_OY":0,"parti24_ALDIGI_OY":0,"parti25_ALDIGI_OY":0,"parti26_ALDIGI_OY":0,"parti27_ALDIGI_OY":0,"parti28_ALDIGI_OY":0,"parti29_ALDIGI_OY":0,"parti30_ALDIGI_OY":0,"bagimsiz1_ALDIGI_OY":3012,"bagimsiz2_ALDIGI_OY":152,"sandik_ID":0,"secmen_SAYISI":8713,"oy_KULLANAN_SECMEN_SAYISI":7534,"itirazli_GECERLI_OY_SAYISI":0,"gecerli_OY_TOPLAMI":7341,"gecersiz_OY_TOPLAMI":193,"itirazsiz_GECERLI_OY_SAYISI":7341},{"dis_TEMSILCILIK_ID":0,"birim_ID":0,"ilce_ID":113,"ilce_ADI":"BULDAN","belde_ID":0,"il_ID":20,"il_ADI":"DENİZLİ","ulke_ID":0,"muhtarlik_ID":0,"muhtarlik_ADI":null,"cezaevi_ID":0,"sandik_NO":null,"sandik_SONUC_TUTANAGI":0,"sandik_DOKUM_CETVELI":0,"denetim_TUTANAGI":0,"bagimsiz_TOPLAM_OY":17207,"gumruk_ID":0,"sandik_RUMUZ":null,"gumruk_SANDIK_TARIHI":null,"birlestirme_TUTANAGI_KURUL":0,"birlestirme_TUTANAGI_ULKE":0,"birlestirme_TUTANAGI_ILCE":0,"birlestirme_TUTANAGI_IL":0,"birlestirme_TUTANAGI_DIS_TEMSILCILIK":0,"birlestirme_TUTANAGI_GUMRUK_ILCE":0,"birlestirme_TUTANAGI_GUMRUK_RUMUZ":0,"birlestirme_TUTANAGI_GUMRUK_KURUL":0,"birlestirme_TUTANAGI_TUMDUNYA":0,"birlestirme_TUTANAGI_ULKELER":0,"birlestirme_TUTANAGI_GUMRUKLER":0,"bagimsiz3_ALDIGI_OY":9411,"bagimsiz4_ALDIGI_OY":0,"bagimsiz5_ALDIGI_OY":0,"bagimsiz6_ALDIGI_OY":0,"bagimsiz7_ALDIGI_OY":0,"bagimsiz8_ALDIGI_OY":0,"bagimsiz9_ALDIGI_OY":0,"bagimsiz10_ALDIGI_OY":0,"bagimsiz11_ALDIGI_OY":0,"bagimsiz12_ALDIGI_OY":0,"bagimsiz13_ALDIGI_OY":0,"bagimsiz14_ALDIGI_OY":0,"bagimsiz15_ALDIGI_OY":0,"bagimsiz16_ALDIGI_OY":0,"bagimsiz17_ALDIGI_OY":0,"bagimsiz18_ALDIGI_OY":0,"bagimsiz19_ALDIGI_OY":0,"bagimsiz20_ALDIGI_OY":0,"bagimsiz21_ALDIGI_OY":0,"bagimsiz22_ALDIGI_OY":0,"bagimsiz23_ALDIGI_OY":0,"bagimsiz24_ALDIGI_OY":0,"bagimsiz25_ALDIGI_OY":0,"bagimsiz26_ALDIGI_OY":0,"bagimsiz27_ALDIGI_OY":0,"bagimsiz28_ALDIGI_OY":0,"bagimsiz29_ALDIGI_OY":0,"bagimsiz30_ALDIGI_OY":0,"bagimsiz31_ALDIGI_OY":0,"bagimsiz32_ALDIGI_OY":0,"bagimsiz33_ALDIGI_OY":0,"bagimsiz34_ALDIGI_OY":0,"bagimsiz35_ALDIGI_OY":0,"bagimsiz36_ALDIGI_OY":0,"bagimsiz37_ALDIGI_OY":0,"bagimsiz38_ALDIGI_OY":0,"bagimsiz39_ALDIGI_OY":0,"bagimsiz40_ALDIGI_OY":0,"bagimsiz41_ALDIGI_OY":0,"bagimsiz42_ALDIGI_OY":0,"bagimsiz43_ALDIGI_OY":0,"bagimsiz44_ALDIGI_OY":0,"bagimsiz45_ALDIGI_OY":0,"bagimsiz46_ALDIGI_OY":0,"bagimsiz47_ALDIGI_OY":0,"bagimsiz48_ALDIGI_OY":0,"bagimsiz49_ALDIGI_OY":0,"bagimsiz50_ALDIGI_OY":0,"ittifak1_ALDIGI_OY":0,"ittifak2_ALDIGI_OY":0,"ittifak3_ALDIGI_OY":0,"ittifak4_ALDIGI_OY":0,"ittifak5_ALDIGI_OY":0,"versiyon":2671,"son_ISLEM_TARIHI":"2014-08-10T16:59:25.000+0000","degisiklik_NEDENI":0,"sandik_SONUC_ID":0,"secim_ID":13340,"secim_TURU":0,"parti1_ALDIGI_OY":0,"parti2_ALDIGI_OY":0,"parti3_ALDIGI_OY":0,"parti4_ALDIGI_OY":0,"parti5_ALDIGI_OY":0,"parti6_ALDIGI_OY":0,"parti7_ALDIGI_OY":0,"parti8_ALDIGI_OY":0,"parti9_ALDIGI_OY":0,"parti10_ALDIGI_OY":0,"parti11_ALDIGI_OY":0,"parti12_ALDIGI_OY":0,"parti13_ALDIGI_OY":0,"parti14_ALDIGI_OY":0,"parti15_ALDIGI_OY":0,"parti16_ALDIGI_OY":0,"parti17_ALDIGI_OY":0,"parti18_ALDIGI_OY":0,"parti19_ALDIGI_OY":0,"parti20_ALDIGI_OY":0,"parti21_ALDIGI_OY":0,"parti22_ALDIGI_OY":0,"parti23_ALDIGI_OY":0,"parti24_ALDIGI_OY":0,"parti25_ALDIGI_OY":0,"parti26_ALDIGI_OY":0,"parti27_ALDIGI_OY":0,"parti28_ALDIGI_OY":0,"parti29_ALDIGI_OY":0,"parti30_ALDIGI_OY":0,"bagimsiz1_ALDIGI_OY":7481,"bagimsiz2_ALDIGI_OY":315,"sandik_ID":0,"secmen_SAYISI":20734,"oy_KULLANAN_SECMEN_SAYISI":17630,"itirazli_GECERLI_OY_SAYISI":0,"gecerli_OY_TOPLAMI":17207,"gecersiz_OY_TOPLAMI":423,"itirazsiz_GECERLI_OY_SAYISI":17207},{"dis_TEMSILCILIK_ID":0,"birim_ID":0,"ilce_ID":122,"ilce_ADI":"ÇAL","belde_ID":0,"il_ID":20,"il_ADI":"DENİZLİ","ulke_ID":0,"muhtarlik_ID":0,"muhtarlik_ADI":null,"cezaevi_ID":0,"sandik_NO":null,"sandik_SONUC_TUTANAGI":0,"sandik_DOKUM_CETVELI":0,"denetim_TUTANAGI":0,"bagimsiz_TOPLAM_OY":14053,"gumruk_ID":0,"sandik_RUMUZ":null,"gumruk_SANDIK_TARIHI":null,"birlestirme_TUTANAGI_KURUL":0,"birlestirme_TUTANAGI_ULKE":0,"birlestirme_TUTANAGI_ILCE":0,"birlestirme_TUTANAGI_IL":0,"birlestirme_TUTANAGI_DIS_TEMSILCILIK":0,"birlestirme_TUTANAGI_GUMRUK_ILCE":0,"birlestirme_TUTANAGI_GUMRUK_RUMUZ":0,"birlestirme_TUTANAGI_GUMRUK_KURUL":0,"birlestirme_TUTANAGI_TUMDUNYA":0,"birlestirme_TUTANAGI_ULKELER":0,"birlestirme_TUTANAGI_GUMRUKLER":0,"bagimsiz3_ALDIGI_OY":8058,"bagimsiz4_ALDIGI_OY":0,"bagimsiz5_ALDIGI_OY":0,"bagimsiz6_ALDIGI_OY":0,"bagimsiz7_ALDIGI_OY":0,"bagimsiz8_ALDIGI_OY":0,"bagimsiz9_ALDIGI_OY":0,"bagimsiz10_ALDIGI_OY":0,"bagimsiz11_ALDIGI_OY":0,"bagimsiz12_ALDIGI_OY":0,"bagimsiz13_ALDIGI_OY":0,"bagimsiz14_ALDIGI_OY":0,"bagimsiz15_ALDIGI_OY":0,"bagimsiz16_ALDIGI_OY":0,"bagimsiz17_ALDIGI_OY":0,"bagimsiz18_ALDIGI_OY":0,"bagimsiz19_ALDIGI_OY":0,"bagimsiz20_ALDIGI_OY":0,"bagimsiz21_ALDIGI_OY":0,"bagimsiz22_ALDIGI_OY":0,"bagimsiz23_ALDIGI_OY":0,"bagimsiz24_ALDIGI_OY":0,"bagimsiz25_ALDIGI_OY":0,"bagimsiz26_ALDIGI_OY":0,"bagimsiz27_ALDIGI_OY":0,"bagimsiz28_ALDIGI_OY":0,"bagimsiz29_ALDIGI_OY":0,"bagimsiz30_ALDIGI_OY":0,"bagimsiz31_ALDIGI_OY":0,"bagimsiz32_ALDIGI_OY":0,"bagimsiz33_ALDIGI_OY":0,"bagimsiz34_ALDIGI_OY":0,"bagimsiz35_ALDIGI_OY":0,"bagimsiz36_ALDIGI_OY":0,"bagimsiz37_ALDIGI_OY":0,"bagimsiz38_ALDIGI_OY":0,"bagimsiz39_ALDIGI_OY":0,"bagimsiz40_ALDIGI_OY":0,"bagimsiz41_ALDIGI_OY":0,"bagimsiz42_ALDIGI_OY":0,"bagimsiz43_ALDIGI_OY":0,"bagimsiz44_ALDIGI_OY":0,"bagimsiz45_ALDIGI_OY":0,"bagimsiz46_ALDIGI_OY":0,"bagimsiz47_ALDIGI_OY":0,"bagimsiz48_ALDIGI_OY":0,"bagimsiz49_ALDIGI_OY":0,"bagimsiz50_ALDIGI_OY":0,"ittifak1_ALDIGI_OY":0,"ittifak2_ALDIGI_OY":0,"ittifak3_ALDIGI_OY":0,"ittifak4_ALDIGI_OY":0,"ittifak5_ALDIGI_OY":0,"versiyon":2671,"son_ISLEM_TARIHI":"2014-08-10T17:20:37.000+0000","degisiklik_NEDENI":0,"sandik_SONUC_ID":0,"secim_ID":13340,"secim_TURU":0,"parti1_ALDIGI_OY":0,"parti2_ALDIGI_OY":0,"parti3_ALDIGI_OY":0,"parti4_ALDIGI_OY":0,"parti5_ALDIGI_OY":0,"parti6_ALDIGI_OY":0,"parti7_ALDIGI_OY":0,"parti8_ALDIGI_OY":0,"parti9_ALDIGI_OY":0,"parti10_ALDIGI_OY":0,"parti11_ALDIGI_OY":0,"parti12_ALDIGI_OY":0,"parti13_ALDIGI_OY":0,"parti14_ALDIGI_OY":0,"parti15_ALDIGI_OY":0,"parti16_ALDIGI_OY":0,"parti17_ALDIGI_OY":0,"parti18_ALDIGI_OY":0,"parti19_ALDIGI_OY":0,"parti20_ALDIGI_OY":0,"parti21_ALDIGI_OY":0,"parti22_ALDIGI_OY":0,"parti23_ALDIGI_OY":0,"parti24_ALDIGI_OY":0,"parti25_ALDIGI_OY":0,"parti26_ALDIGI_OY":0,"parti27_ALDIGI_OY":0,"parti28_ALDIGI_OY":0,"parti29_ALDIGI_OY":0,"parti30_ALDIGI_OY":0,"bagimsiz1_ALDIGI_OY":5726,"bagimsiz2_ALDIGI_OY":269,"sandik_ID":0,"secmen_SAYISI":16482,"oy_KULLANAN_SECMEN_SAYISI":14445,"itirazli_GECERLI_OY_SAYISI":0,"gecerli_OY_TOPLAMI":14053,"gecersiz_OY_TOPLAMI":392,"itirazsiz_GECERLI_OY_SAYISI":14053},{"dis_TEMSILCILIK_ID":0,"birim_ID":0,"ilce_ID":124,"ilce_ADI":"ÇAMELİ","belde_ID":0,"il_ID":20,"il_ADI":"DENİZLİ","ulke_ID":0,"muhtarlik_ID":0,"muhtarlik_ADI":null,"cezaevi_ID":0,"sandik_NO":null,"sandik_SONUC_TUTANAGI":0,"sandik_DOKUM_CETVELI":0,"denetim_TUTANAGI":0,"bagimsiz_TOPLAM_OY":11692,"gumruk_ID":0,"sandik_RUMUZ":null,"gumruk_SANDIK_TARIHI":null,"birlestirme_TUTANAGI_KURUL":0,"birlestirme_TUTANAGI_ULKE":0,"birlestirme_TUTANAGI_ILCE":0,"birlestirme_TUTANAGI_IL":0,"birlestirme_TUTANAGI_DIS_TEMSILCILIK":0,"birlestirme_TUTANAGI_GUMRUK_ILCE":0,"birlestirme_TUTANAGI_GUMRUK_RUMUZ":0,"birlestirme_TUTANAGI_GUMRUK_KURUL":0,"birlestirme_TUTANAGI_TUMDUNYA":0,"birlestirme_TUTANAGI_ULKELER":0,"birlestirme_TUTANAGI_GUMRUKLER":0,"bagimsiz3_ALDIGI_OY":3130,"bagimsiz4_ALDIGI_OY":0,"bagimsiz5_ALDIGI_OY":0,"bagimsiz6_ALDIGI_OY":0,"bagimsiz7_ALDIGI_OY":0,"bagimsiz8_ALDIGI_OY":0,"bagimsiz9_ALDIGI_OY":0,"bagimsiz10_ALDIGI_OY":0,"bagimsiz11_ALDIGI_OY":0,"bagimsiz12_ALDIGI_OY":0,"bagimsiz13_ALDIGI_OY":0,"bagimsiz14_ALDIGI_OY":0,"bagimsiz15_ALDIGI_OY":0,"bagimsiz16_ALDIGI_OY":0,"bagimsiz17_ALDIGI_OY":0,"bagimsiz18_ALDIGI_OY":0,"bagimsiz19_ALDIGI_OY":0,"bagimsiz20_ALDIGI_OY":0,"bagimsiz21_ALDIGI_OY":0,"bagimsiz22_ALDIGI_OY":0,"bagimsiz23_ALDIGI_OY":0,"bagimsiz24_ALDIGI_OY":0,"bagimsiz25_ALDIGI_OY":0,"bagimsiz26_ALDIGI_OY":0,"bagimsiz27_ALDIGI_OY":0,"bagimsiz28_ALDIGI_OY":0,"bagimsiz29_ALDIGI_OY":0,"bagimsiz30_ALDIGI_OY":0,"bagimsiz31_ALDIGI_OY":0,"bagimsiz32_ALDIGI_OY":0,"bagimsiz33_ALDIGI_OY":0,"bagimsiz34_ALDIGI_OY":0,"bagimsiz35_ALDIGI_OY":0,"bagimsiz36_ALDIGI_OY":0,"bagimsiz37_ALDIGI_OY":0,"bagimsiz38_ALDIGI_OY":0,"bagimsiz39_ALDIGI_OY":0,"bagimsiz40_ALDIGI_OY":0,"bagimsiz41_ALDIGI_OY":0,"bagimsiz42_ALDIGI_OY":0,"bagimsiz43_ALDIGI_OY":0,"bagimsiz44_ALDIGI_OY":0,"bagimsiz45_ALDIGI_OY":0,"bagimsiz46_ALDIGI_OY":0,"bagimsiz47_ALDIGI_OY":0,"bagimsiz48_ALDIGI_OY":0,"bagimsiz49_ALDIGI_OY":0,"bagimsiz50_ALDIGI_OY":0,"ittifak1_ALDIGI_OY":0,"ittifak2_ALDIGI_OY":0,"ittifak3_ALDIGI_OY":0,"ittifak4_ALDIGI_OY":0,"ittifak5_ALDIGI_OY":0,"versiyon":2671,"son_ISLEM_TARIHI":"2014-08-10T16:28:24.000+0000","degisiklik_NEDENI":0,"sandik_SONUC_ID":0,"secim_ID":13340,"secim_TURU":0,"parti1_ALDIGI_OY":0,"parti2_ALDIGI_OY":0,"parti3_ALDIGI_OY":0,"parti4_ALDIGI_OY":0,"parti5_ALDIGI_OY":0,"parti6_ALDIGI_OY":0,"parti7_ALDIGI_OY":0,"parti8_ALDIGI_OY":0,"parti9_ALDIGI_OY":0,"parti10_ALDIGI_OY":0,"parti11_ALDIGI_OY":0,"parti12_ALDIGI_OY":0,"parti13_ALDIGI_OY":0,"parti14_ALDIGI_OY":0,"parti15_ALDIGI_OY":0,"parti16_ALDIGI_OY":0,"parti17_ALDIGI_OY":0,"parti18_ALDIGI_OY":0,"parti19_ALDIGI_OY":0,"parti20_ALDIGI_OY":0,"parti21_ALDIGI_OY":0,"parti22_ALDIGI_OY":0,"parti23_ALDIGI_OY":0,"parti24_ALDIGI_OY":0,"parti25_ALDIGI_OY":0,"parti26_ALDIGI_OY":0,"parti27_ALDIGI_OY":0,"parti28_ALDIGI_OY":0,"parti29_ALDIGI_OY":0,"parti30_ALDIGI_OY":0,"bagimsiz1_ALDIGI_OY":8271,"bagimsiz2_ALDIGI_OY":291,"sandik_ID":0,"secmen_SAYISI":14857,"oy_KULLANAN_SECMEN_SAYISI":12162,"itirazli_GECERLI_OY_SAYISI":0,"gecerli_OY_TOPLAMI":11692,"gecersiz_OY_TOPLAMI":470,"itirazsiz_GECERLI_OY_SAYISI":11692},{"dis_TEMSILCILIK_ID":0,"birim_ID":0,"ilce_ID":131,"ilce_ADI":"ÇARDAK","belde_ID":0,"il_ID":20,"il_ADI":"DENİZLİ","ulke_ID":0,"muhtarlik_ID":0,"muhtarlik_ADI":null,"cezaevi_ID":0,"sandik_NO":null,"sandik_SONUC_TUTANAGI":0,"sandik_DOKUM_CETVELI":0,"denetim_TUTANAGI":0,"bagimsiz_TOPLAM_OY":5673,"gumruk_ID":0,"sandik_RUMUZ":null,"gumruk_SANDIK_TARIHI":null,"birlestirme_TUTANAGI_KURUL":0,"birlestirme_TUTANAGI_ULKE":0,"birlestirme_TUTANAGI_ILCE":0,"birlestirme_TUTANAGI_IL":0,"birlestirme_TUTANAGI_DIS_TEMSILCILIK":0,"birlestirme_TUTANAGI_GUMRUK_ILCE":0,"birlestirme_TUTANAGI_GUMRUK_RUMUZ":0,"birlestirme_TUTANAGI_GUMRUK_KURUL":0,"birlestirme_TUTANAGI_TUMDUNYA":0,"birlestirme_TUTANAGI_ULKELER":0,"birlestirme_TUTANAGI_GUMRUKLER":0,"bagimsiz3_ALDIGI_OY":3161,"bagimsiz4_ALDIGI_OY":0,"bagimsiz5_ALDIGI_OY":0,"bagimsiz6_ALDIGI_OY":0,"bagimsiz7_ALDIGI_OY":0,"bagimsiz8_ALDIGI_OY":0,"bagimsiz9_ALDIGI_OY":0,"bagimsiz10_ALDIGI_OY":0,"bagimsiz11_ALDIGI_OY":0,"bagimsiz12_ALDIGI_OY":0,"bagimsiz13_ALDIGI_OY":0,"bagimsiz14_ALDIGI_OY":0,"bagimsiz15_ALDIGI_OY":0,"bagimsiz16_ALDIGI_OY":0,"bagimsiz17_ALDIGI_OY":0,"bagimsiz18_ALDIGI_OY":0,"bagimsiz19_ALDIGI_OY":0,"bagimsiz20_ALDIGI_OY":0,"bagimsiz21_ALDIGI_OY":0,"bagimsiz22_ALDIGI_OY":0,"bagimsiz23_ALDIGI_OY":0,"bagimsiz24_ALDIGI_OY":0,"bagimsiz25_ALDIGI_OY":0,"bagimsiz26_ALDIGI_OY":0,"bagimsiz27_ALDIGI_OY":0,"bagimsiz28_ALDIGI_OY":0,"bagimsiz29_ALDIGI_OY":0,"bagimsiz30_ALDIGI_OY":0,"bagimsiz31_ALDIGI_OY":0,"bagimsiz32_ALDIGI_OY":0,"bagimsiz33_ALDIGI_OY":0,"bagimsiz34_ALDIGI_OY":0,"bagimsiz35_ALDIGI_OY":0,"bagimsiz36_ALDIGI_OY":0,"bagimsiz37_ALDIGI_OY":0,"bagimsiz38_ALDIGI_OY":0,"bagimsiz39_ALDIGI_OY":0,"bagimsiz40_ALDIGI_OY":0,"bagimsiz41_ALDIGI_OY":0,"bagimsiz42_ALDIGI_OY":0,"bagimsiz43_ALDIGI_OY":0,"bagimsiz44_ALDIGI_OY":0,"bagimsiz45_ALDIGI_OY":0,"bagimsiz46_ALDIGI_OY":0,"bagimsiz47_ALDIGI_OY":0,"bagimsiz48_ALDIGI_OY":0,"bagimsiz49_ALDIGI_OY":0,"bagimsiz50_ALDIGI_OY":0,"ittifak1_ALDIGI_OY":0,"ittifak2_ALDIGI_OY":0,"ittifak3_ALDIGI_OY":0,"ittifak4_ALDIGI_OY":0,"ittifak5_ALDIGI_OY":0,"versiyon":2671,"son_ISLEM_TARIHI":"2014-08-10T16:11:26.000+0000","degisiklik_NEDENI":0,"sandik_SONUC_ID":0,"secim_ID":13340,"secim_TURU":0,"parti1_ALDIGI_OY":0,"parti2_ALDIGI_OY":0,"parti3_ALDIGI_OY":0,"parti4_ALDIGI_OY":0,"parti5_ALDIGI_OY":0,"parti6_ALDIGI_OY":0,"parti7_ALDIGI_OY":0,"parti8_ALDIGI_OY":0,"parti9_ALDIGI_OY":0,"parti10_ALDIGI_OY":0,"parti11_ALDIGI_OY":0,"parti12_ALDIGI_OY":0,"parti13_ALDIGI_OY":0,"parti14_ALDIGI_OY":0,"parti15_ALDIGI_OY":0,"parti16_ALDIGI_OY":0,"parti17_ALDIGI_OY":0,"parti18_ALDIGI_OY":0,"parti19_ALDIGI_OY":0,"parti20_ALDIGI_OY":0,"parti21_ALDIGI_OY":0,"parti22_ALDIGI_OY":0,"parti23_ALDIGI_OY":0,"parti24_ALDIGI_OY":0,"parti25_ALDIGI_OY":0,"parti26_ALDIGI_OY":0,"parti27_ALDIGI_OY":0,"parti28_ALDIGI_OY":0,"parti29_ALDIGI_OY":0,"parti30_ALDIGI_OY":0,"bagimsiz1_ALDIGI_OY":2411,"bagimsiz2_ALDIGI_OY":101,"sandik_ID":0,"secmen_SAYISI":6928,"oy_KULLANAN_SECMEN_SAYISI":5834,"itirazli_GECERLI_OY_SAYISI":0,"gecerli_OY_TOPLAMI":5673,"gecersiz_OY_TOPLAMI":161,"itirazsiz_GECERLI_OY_SAYISI":5673},{"dis_TEMSILCILIK_ID":0,"birim_ID":0,"ilce_ID":155,"ilce_ADI":"ÇİVRİL","belde_ID":0,"il_ID":20,"il_ADI":"DENİZLİ","ulke_ID":0,"muhtarlik_ID":0,"muhtarlik_ADI":null,"cezaevi_ID":0,"sandik_NO":null,"sandik_SONUC_TUTANAGI":0,"sandik_DOKUM_CETVELI":0,"denetim_TUTANAGI":0,"bagimsiz_TOPLAM_OY":37103,"gumruk_ID":0,"sandik_RUMUZ":null,"gumruk_SANDIK_TARIHI":null,"birlestirme_TUTANAGI_KURUL":0,"birlestirme_TUTANAGI_ULKE":0,"birlestirme_TUTANAGI_ILCE":0,"birlestirme_TUTANAGI_IL":0,"birlestirme_TUTANAGI_DIS_TEMSILCILIK":0,"birlestirme_TUTANAGI_GUMRUK_ILCE":0,"birlestirme_TUTANAGI_GUMRUK_RUMUZ":0,"birlestirme_TUTANAGI_GUMRUK_KURUL":0,"birlestirme_TUTANAGI_TUMDUNYA":0,"birlestirme_TUTANAGI_ULKELER":0,"birlestirme_TUTANAGI_GUMRUKLER":0,"bagimsiz3_ALDIGI_OY":19427,"bagimsiz4_ALDIGI_OY":0,"bagimsiz5_ALDIGI_OY":0,"bagimsiz6_ALDIGI_OY":0,"bagimsiz7_ALDIGI_OY":0,"bagimsiz8_ALDIGI_OY":0,"bagimsiz9_ALDIGI_OY":0,"bagimsiz10_ALDIGI_OY":0,"bagimsiz11_ALDIGI_OY":0,"bagimsiz12_ALDIGI_OY":0,"bagimsiz13_ALDIGI_OY":0,"bagimsiz14_ALDIGI_OY":0,"bagimsiz15_ALDIGI_OY":0,"bagimsiz16_ALDIGI_OY":0,"bagimsiz17_ALDIGI_OY":0,"bagimsiz18_ALDIGI_OY":0,"bagimsiz19_ALDIGI_OY":0,"bagimsiz20_ALDIGI_OY":0,"bagimsiz21_ALDIGI_OY":0,"bagimsiz22_ALDIGI_OY":0,"bagimsiz23_ALDIGI_OY":0,"bagimsiz24_ALDIGI_OY":0,"bagimsiz25_ALDIGI_OY":0,"bagimsiz26_ALDIGI_OY":0,"bagimsiz27_ALDIGI_OY":0,"bagimsiz28_ALDIGI_OY":0,"bagimsiz29_ALDIGI_OY":0,"bagimsiz30_ALDIGI_OY":0,"bagimsiz31_ALDIGI_OY":0,"bagimsiz32_ALDIGI_OY":0,"bagimsiz33_ALDIGI_OY":0,"bagimsiz34_ALDIGI_OY":0,"bagimsiz35_ALDIGI_OY":0,"bagimsiz36_ALDIGI_OY":0,"bagimsiz37_ALDIGI_OY":0,"bagimsiz38_ALDIGI_OY":0,"bagimsiz39_ALDIGI_OY":0,"bagimsiz40_ALDIGI_OY":0,"bagimsiz41_ALDIGI_OY":0,"bagimsiz42_ALDIGI_OY":0,"bagimsiz43_ALDIGI_OY":0,"bagimsiz44_ALDIGI_OY":0,"bagimsiz45_ALDIGI_OY":0,"bagimsiz46_ALDIGI_OY":0,"bagimsiz47_ALDIGI_OY":0,"bagimsiz48_ALDIGI_OY":0,"bagimsiz49_ALDIGI_OY":0,"bagimsiz50_ALDIGI_OY":0,"ittifak1_ALDIGI_OY":0,"ittifak2_ALDIGI_OY":0,"ittifak3_ALDIGI_OY":0,"ittifak4_ALDIGI_OY":0,"ittifak5_ALDIGI_OY":0,"versiyon":2671,"son_ISLEM_TARIHI":"2014-08-11T13:50:34.000+0000","degisiklik_NEDENI":1,"sandik_SONUC_ID":0,"secim_ID":13340,"secim_TURU":0,"parti1_ALDIGI_OY":0,"parti2_ALDIGI_OY":0,"parti3_ALDIGI_OY":0,"parti4_ALDIGI_OY":0,"parti5_ALDIGI_OY":0,"parti6_ALDIGI_OY":0,"parti7_ALDIGI_OY":0,"parti8_ALDIGI_OY":0,"parti9_ALDIGI_OY":0,"parti10_ALDIGI_OY":0,"parti11_ALDIGI_OY":0,"parti12_ALDIGI_OY":0,"parti13_ALDIGI_OY":0,"parti14_ALDIGI_OY":0,"parti15_ALDIGI_OY":0,"parti16_ALDIGI_OY":0,"parti17_ALDIGI_OY":0,"parti18_ALDIGI_OY":0,"parti19_ALDIGI_OY":0,"parti20_ALDIGI_OY":0,"parti21_ALDIGI_OY":0,"parti22_ALDIGI_OY":0,"parti23_ALDIGI_OY":0,"parti24_ALDIGI_OY":0,"parti25_ALDIGI_OY":0,"parti26_ALDIGI_OY":0,"parti27_ALDIGI_OY":0,"parti28_ALDIGI_OY":0,"parti29_ALDIGI_OY":0,"parti30_ALDIGI_OY":0,"bagimsiz1_ALDIGI_OY":16894,"bagimsiz2_ALDIGI_OY":782,"sandik_ID":0,"secmen_SAYISI":45393,"oy_KULLANAN_SECMEN_SAYISI":38247,"itirazli_GECERLI_OY_SAYISI":0,"gecerli_OY_TOPLAMI":37103,"gecersiz_OY_TOPLAMI":1144,"itirazsiz_GECERLI_OY_SAYISI":37103},{"dis_TEMSILCILIK_ID":0,"birim_ID":0,"ilce_ID":268,"ilce_ADI":"GÜNEY","belde_ID":0,"il_ID":20,"il_ADI":"DENİZLİ","ulke_ID":0,"muhtarlik_ID":0,"muhtarlik_ADI":null,"cezaevi_ID":0,"sandik_NO":null,"sandik_SONUC_TUTANAGI":0,"sandik_DOKUM_CETVELI":0,"denetim_TUTANAGI":0,"bagimsiz_TOPLAM_OY":7030,"gumruk_ID":0,"sandik_RUMUZ":null,"gumruk_SANDIK_TARIHI":null,"birlestirme_TUTANAGI_KURUL":0,"birlestirme_TUTANAGI_ULKE":0,"birlestirme_TUTANAGI_ILCE":0,"birlestirme_TUTANAGI_IL":0,"birlestirme_TUTANAGI_DIS_TEMSILCILIK":0,"birlestirme_TUTANAGI_GUMRUK_ILCE":0,"birlestirme_TUTANAGI_GUMRUK_RUMUZ":0,"birlestirme_TUTANAGI_GUMRUK_KURUL":0,"birlestirme_TUTANAGI_TUMDUNYA":0,"birlestirme_TUTANAGI_ULKELER":0,"birlestirme_TUTANAGI_GUMRUKLER":0,"bagimsiz3_ALDIGI_OY":3534,"bagimsiz4_ALDIGI_OY":0,"bagimsiz5_ALDIGI_OY":0,"bagimsiz6_ALDIGI_OY":0,"bagimsiz7_ALDIGI_OY":0,"bagimsiz8_ALDIGI_OY":0,"bagimsiz9_ALDIGI_OY":0,"bagimsiz10_ALDIGI_OY":0,"bagimsiz11_ALDIGI_OY":0,"bagimsiz12_ALDIGI_OY":0,"bagimsiz13_ALDIGI_OY":0,"bagimsiz14_ALDIGI_OY":0,"bagimsiz15_ALDIGI_OY":0,"bagimsiz16_ALDIGI_OY":0,"bagimsiz17_ALDIGI_OY":0,"bagimsiz18_ALDIGI_OY":0,"bagimsiz19_ALDIGI_OY":0,"bagimsiz20_ALDIGI_OY":0,"bagimsiz21_ALDIGI_OY":0,"bagimsiz22_ALDIGI_OY":0,"bagimsiz23_ALDIGI_OY":0,"bagimsiz24_ALDIGI_OY":0,"bagimsiz25_ALDIGI_OY":0,"bagimsiz26_ALDIGI_OY":0,"bagimsiz27_ALDIGI_OY":0,"bagimsiz28_ALDIGI_OY":0,"bagimsiz29_ALDIGI_OY":0,"bagimsiz30_ALDIGI_OY":0,"bagimsiz31_ALDIGI_OY":0,"bagimsiz32_ALDIGI_OY":0,"bagimsiz33_ALDIGI_OY":0,"bagimsiz34_ALDIGI_OY":0,"bagimsiz35_ALDIGI_OY":0,"bagimsiz36_ALDIGI_OY":0,"bagimsiz37_ALDIGI_OY":0,"bagimsiz38_ALDIGI_OY":0,"bagimsiz39_ALDIGI_OY":0,"bagimsiz40_ALDIGI_OY":0,"bagimsiz41_ALDIGI_OY":0,"bagimsiz42_ALDIGI_OY":0,"bagimsiz43_ALDIGI_OY":0,"bagimsiz44_ALDIGI_OY":0,"bagimsiz45_ALDIGI_OY":0,"bagimsiz46_ALDIGI_OY":0,"bagimsiz47_ALDIGI_OY":0,"bagimsiz48_ALDIGI_OY":0,"bagimsiz49_ALDIGI_OY":0,"bagimsiz50_ALDIGI_OY":0,"ittifak1_ALDIGI_OY":0,"ittifak2_ALDIGI_OY":0,"ittifak3_ALDIGI_OY":0,"ittifak4_ALDIGI_OY":0,"ittifak5_ALDIGI_OY":0,"versiyon":2671,"son_ISLEM_TARIHI":"2014-08-10T17:11:27.000+0000","degisiklik_NEDENI":0,"sandik_SONUC_ID":0,"secim_ID":13340,"secim_TURU":0,"parti1_ALDIGI_OY":0,"parti2_ALDIGI_OY":0,"parti3_ALDIGI_OY":0,"parti4_ALDIGI_OY":0,"parti5_ALDIGI_OY":0,"parti6_ALDIGI_OY":0,"parti7_ALDIGI_OY":0,"parti8_ALDIGI_OY":0,"parti9_ALDIGI_OY":0,"parti10_ALDIGI_OY":0,"parti11_ALDIGI_OY":0,"parti12_ALDIGI_OY":0,"parti13_ALDIGI_OY":0,"parti14_ALDIGI_OY":0,"parti15_ALDIGI_OY":0,"parti16_ALDIGI_OY":0,"parti17_ALDIGI_OY":0,"parti18_ALDIGI_OY":0,"parti19_ALDIGI_OY":0,"parti20_ALDIGI_OY":0,"parti21_ALDIGI_OY":0,"parti22_ALDIGI_OY":0,"parti23_ALDIGI_OY":0,"parti24_ALDIGI_OY":0,"parti25_ALDIGI_OY":0,"parti26_ALDIGI_OY":0,"parti27_ALDIGI_OY":0,"parti28_ALDIGI_OY":0,"parti29_ALDIGI_OY":0,"parti30_ALDIGI_OY":0,"bagimsiz1_ALDIGI_OY":3321,"bagimsiz2_ALDIGI_OY":175,"sandik_ID":0,"secmen_SAYISI":8559,"oy_KULLANAN_SECMEN_SAYISI":7414,"itirazli_GECERLI_OY_SAYISI":0,"gecerli_OY_TOPLAMI":7030,"gecersiz_OY_TOPLAMI":384,"itirazsiz_GECERLI_OY_SAYISI":7030},{"dis_TEMSILCILIK_ID":0,"birim_ID":0,"ilce_ID":696,"ilce_ADI":"HONAZ","belde_ID":0,"il_ID":20,"il_ADI":"DENİZLİ","ulke_ID":0,"muhtarlik_ID":0,"muhtarlik_ADI":null,"cezaevi_ID":0,"sandik_NO":null,"sandik_SONUC_TUTANAGI":0,"sandik_DOKUM_CETVELI":0,"denetim_TUTANAGI":0,"bagimsiz_TOPLAM_OY":17049,"gumruk_ID":0,"sandik_RUMUZ":null,"gumruk_SANDIK_TARIHI":null,"birlestirme_TUTANAGI_KURUL":0,"birlestirme_TUTANAGI_ULKE":0,"birlestirme_TUTANAGI_ILCE":0,"birlestirme_TUTANAGI_IL":0,"birlestirme_TUTANAGI_DIS_TEMSILCILIK":0,"birlestirme_TUTANAGI_GUMRUK_ILCE":0,"birlestirme_TUTANAGI_GUMRUK_RUMUZ":0,"birlestirme_TUTANAGI_GUMRUK_KURUL":0,"birlestirme_TUTANAGI_TUMDUNYA":0,"birlestirme_TUTANAGI_ULKELER":0,"birlestirme_TUTANAGI_GUMRUKLER":0,"bagimsiz3_ALDIGI_OY":8620,"bagimsiz4_ALDIGI_OY":0,"bagimsiz5_ALDIGI_OY":0,"bagimsiz6_ALDIGI_OY":0,"bagimsiz7_ALDIGI_OY":0,"bagimsiz8_ALDIGI_OY":0,"bagimsiz9_ALDIGI_OY":0,"bagimsiz10_ALDIGI_OY":0,"bagimsiz11_ALDIGI_OY":0,"bagimsiz12_ALDIGI_OY":0,"bagimsiz13_ALDIGI_OY":0,"bagimsiz14_ALDIGI_OY":0,"bagimsiz15_ALDIGI_OY":0,"bagimsiz16_ALDIGI_OY":0,"bagimsiz17_ALDIGI_OY":0,"bagimsiz18_ALDIGI_OY":0,"bagimsiz19_ALDIGI_OY":0,"bagimsiz20_ALDIGI_OY":0,"bagimsiz21_ALDIGI_OY":0,"bagimsiz22_ALDIGI_OY":0,"bagimsiz23_ALDIGI_OY":0,"bagimsiz24_ALDIGI_OY":0,"bagimsiz25_ALDIGI_OY":0,"bagimsiz26_ALDIGI_OY":0,"bagimsiz27_ALDIGI_OY":0,"bagimsiz28_ALDIGI_OY":0,"bagimsiz29_ALDIGI_OY":0,"bagimsiz30_ALDIGI_OY":0,"bagimsiz31_ALDIGI_OY":0,"bagimsiz32_ALDIGI_OY":0,"bagimsiz33_ALDIGI_OY":0,"bagimsiz34_ALDIGI_OY":0,"bagimsiz35_ALDIGI_OY":0,"bagimsiz36_ALDIGI_OY":0,"bagimsiz37_ALDIGI_OY":0,"bagimsiz38_ALDIGI_OY":0,"bagimsiz39_ALDIGI_OY":0,"bagimsiz40_ALDIGI_OY":0,"bagimsiz41_ALDIGI_OY":0,"bagimsiz42_ALDIGI_OY":0,"bagimsiz43_ALDIGI_OY":0,"bagimsiz44_ALDIGI_OY":0,"bagimsiz45_ALDIGI_OY":0,"bagimsiz46_ALDIGI_OY":0,"bagimsiz47_ALDIGI_OY":0,"bagimsiz48_ALDIGI_OY":0,"bagimsiz49_ALDIGI_OY":0,"bagimsiz50_ALDIGI_OY":0,"ittifak1_ALDIGI_OY":0,"ittifak2_ALDIGI_OY":0,"ittifak3_ALDIGI_OY":0,"ittifak4_ALDIGI_OY":0,"ittifak5_ALDIGI_OY":0,"versiyon":2671,"son_ISLEM_TARIHI":"2014-08-10T17:43:23.000+0000","degisiklik_NEDENI":0,"sandik_SONUC_ID":0,"secim_ID":13340,"secim_TURU":0,"parti1_ALDIGI_OY":0,"parti2_ALDIGI_OY":0,"parti3_ALDIGI_OY":0,"parti4_ALDIGI_OY":0,"parti5_ALDIGI_OY":0,"parti6_ALDIGI_OY":0,"parti7_ALDIGI_OY":0,"parti8_ALDIGI_OY":0,"parti9_ALDIGI_OY":0,"parti10_ALDIGI_OY":0,"parti11_ALDIGI_OY":0,"parti12_ALDIGI_OY":0,"parti13_ALDIGI_OY":0,"parti14_ALDIGI_OY":0,"parti15_ALDIGI_OY":0,"parti16_ALDIGI_OY":0,"parti17_ALDIGI_OY":0,"parti18_ALDIGI_OY":0,"parti19_ALDIGI_OY":0,"parti20_ALDIGI_OY":0,"parti21_ALDIGI_OY":0,"parti22_ALDIGI_OY":0,"parti23_ALDIGI_OY":0,"parti24_ALDIGI_OY":0,"parti25_ALDIGI_OY":0,"parti26_ALDIGI_OY":0,"parti27_ALDIGI_OY":0,"parti28_ALDIGI_OY":0,"parti29_ALDIGI_OY":0,"parti30_ALDIGI_OY":0,"bagimsiz1_ALDIGI_OY":7827,"bagimsiz2_ALDIGI_OY":602,"sandik_ID":0,"secmen_SAYISI":21402,"oy_KULLANAN_SECMEN_SAYISI":17386,"itirazli_GECERLI_OY_SAYISI":0,"gecerli_OY_TOPLAMI":17049,"gecersiz_OY_TOPLAMI":337,"itirazsiz_GECERLI_OY_SAYISI":17049},{"dis_TEMSILCILIK_ID":0,"birim_ID":0,"ilce_ID":321,"ilce_ADI":"KALE","belde_ID":0,"il_ID":20,"il_ADI":"DENİZLİ","ulke_ID":0,"muhtarlik_ID":0,"muhtarlik_ADI":null,"cezaevi_ID":0,"sandik_NO":null,"sandik_SONUC_TUTANAGI":0,"sandik_DOKUM_CETVELI":0,"denetim_TUTANAGI":0,"bagimsiz_TOPLAM_OY":12165,"gumruk_ID":0,"sandik_RUMUZ":null,"gumruk_SANDIK_TARIHI":null,"birlestirme_TUTANAGI_KURUL":0,"birlestirme_TUTANAGI_ULKE":0,"birlestirme_TUTANAGI_ILCE":0,"birlestirme_TUTANAGI_IL":0,"birlestirme_TUTANAGI_DIS_TEMSILCILIK":0,"birlestirme_TUTANAGI_GUMRUK_ILCE":0,"birlestirme_TUTANAGI_GUMRUK_RUMUZ":0,"birlestirme_TUTANAGI_GUMRUK_KURUL":0,"birlestirme_TUTANAGI_TUMDUNYA":0,"birlestirme_TUTANAGI_ULKELER":0,"birlestirme_TUTANAGI_GUMRUKLER":0,"bagimsiz3_ALDIGI_OY":4222,"bagimsiz4_ALDIGI_OY":0,"bagimsiz5_ALDIGI_OY":0,"bagimsiz6_ALDIGI_OY":0,"bagimsiz7_ALDIGI_OY":0,"bagimsiz8_ALDIGI_OY":0,"bagimsiz9_ALDIGI_OY":0,"bagimsiz10_ALDIGI_OY":0,"bagimsiz11_ALDIGI_OY":0,"bagimsiz12_ALDIGI_OY":0,"bagimsiz13_ALDIGI_OY":0,"bagimsiz14_ALDIGI_OY":0,"bagimsiz15_ALDIGI_OY":0,"bagimsiz16_ALDIGI_OY":0,"bagimsiz17_ALDIGI_OY":0,"bagimsiz18_ALDIGI_OY":0,"bagimsiz19_ALDIGI_OY":0,"bagimsiz20_ALDIGI_OY":0,"bagimsiz21_ALDIGI_OY":0,"bagimsiz22_ALDIGI_OY":0,"bagimsiz23_ALDIGI_OY":0,"bagimsiz24_ALDIGI_OY":0,"bagimsiz25_ALDIGI_OY":0,"bagimsiz26_ALDIGI_OY":0,"bagimsiz27_ALDIGI_OY":0,"bagimsiz28_ALDIGI_OY":0,"bagimsiz29_ALDIGI_OY":0,"bagimsiz30_ALDIGI_OY":0,"bagimsiz31_ALDIGI_OY":0,"bagimsiz32_ALDIGI_OY":0,"bagimsiz33_ALDIGI_OY":0,"bagimsiz34_ALDIGI_OY":0,"bagimsiz35_ALDIGI_OY":0,"bagimsiz36_ALDIGI_OY":0,"bagimsiz37_ALDIGI_OY":0,"bagimsiz38_ALDIGI_OY":0,"bagimsiz39_ALDIGI_OY":0,"bagimsiz40_ALDIGI_OY":0,"bagimsiz41_ALDIGI_OY":0,"bagimsiz42_ALDIGI_OY":0,"bagimsiz43_ALDIGI_OY":0,"bagimsiz44_ALDIGI_OY":0,"bagimsiz45_ALDIGI_OY":0,"bagimsiz46_ALDIGI_OY":0,"bagimsiz47_ALDIGI_OY":0,"bagimsiz48_ALDIGI_OY":0,"bagimsiz49_ALDIGI_OY":0,"bagimsiz50_ALDIGI_OY":0,"ittifak1_ALDIGI_OY":0,"ittifak2_ALDIGI_OY":0,"ittifak3_ALDIGI_OY":0,"ittifak4_ALDIGI_OY":0,"ittifak5_ALDIGI_OY":0,"versiyon":2671,"son_ISLEM_TARIHI":"2014-08-10T16:39:53.000+0000","degisiklik_NEDENI":0,"sandik_SONUC_ID":0,"secim_ID":13340,"secim_TURU":0,"parti1_ALDIGI_OY":0,"parti2_ALDIGI_OY":0,"parti3_ALDIGI_OY":0,"parti4_ALDIGI_OY":0,"parti5_ALDIGI_OY":0,"parti6_ALDIGI_OY":0,"parti7_ALDIGI_OY":0,"parti8_ALDIGI_OY":0,"parti9_ALDIGI_OY":0,"parti10_ALDIGI_OY":0,"parti11_ALDIGI_OY":0,"parti12_ALDIGI_OY":0,"parti13_ALDIGI_OY":0,"parti14_ALDIGI_OY":0,"parti15_ALDIGI_OY":0,"parti16_ALDIGI_OY":0,"parti17_ALDIGI_OY":0,"parti18_ALDIGI_OY":0,"parti19_ALDIGI_OY":0,"parti20_ALDIGI_OY":0,"parti21_ALDIGI_OY":0,"parti22_ALDIGI_OY":0,"parti23_ALDIGI_OY":0,"parti24_ALDIGI_OY":0,"parti25_ALDIGI_OY":0,"parti26_ALDIGI_OY":0,"parti27_ALDIGI_OY":0,"parti28_ALDIGI_OY":0,"parti29_ALDIGI_OY":0,"parti30_ALDIGI_OY":0,"bagimsiz1_ALDIGI_OY":7674,"bagimsiz2_ALDIGI_OY":269,"sandik_ID":0,"secmen_SAYISI":15384,"oy_KULLANAN_SECMEN_SAYISI":12528,"itirazli_GECERLI_OY_SAYISI":0,"gecerli_OY_TOPLAMI":12165,"gecersiz_OY_TOPLAMI":363,"itirazsiz_GECERLI_OY_SAYISI":12165},{"dis_TEMSILCILIK_ID":0,"birim_ID":0,"ilce_ID":1035,"ilce_ADI":"MERKEZEFENDİ","belde_ID":0,"il_ID":20,"il_ADI":"DENİZLİ","ulke_ID":0,"muhtarlik_ID":0,"muhtarlik_ADI":null,"cezaevi_ID":0,"sandik_NO":null,"sandik_SONUC_TUTANAGI":0,"sandik_DOKUM_CETVELI":0,"denetim_TUTANAGI":0,"bagimsiz_TOPLAM_OY":153960,"gumruk_ID":0,"sandik_RUMUZ":null,"gumruk_SANDIK_TARIHI":null,"birlestirme_TUTANAGI_KURUL":0,"birlestirme_TUTANAGI_ULKE":0,"birlestirme_TUTANAGI_ILCE":0,"birlestirme_TUTANAGI_IL":0,"birlestirme_TUTANAGI_DIS_TEMSILCILIK":0,"birlestirme_TUTANAGI_GUMRUK_ILCE":0,"birlestirme_TUTANAGI_GUMRUK_RUMUZ":0,"birlestirme_TUTANAGI_GUMRUK_KURUL":0,"birlestirme_TUTANAGI_TUMDUNYA":0,"birlestirme_TUTANAGI_ULKELER":0,"birlestirme_TUTANAGI_GUMRUKLER":0,"bagimsiz3_ALDIGI_OY":78909,"bagimsiz4_ALDIGI_OY":0,"bagimsiz5_ALDIGI_OY":0,"bagimsiz6_ALDIGI_OY":0,"bagimsiz7_ALDIGI_OY":0,"bagimsiz8_ALDIGI_OY":0,"bagimsiz9_ALDIGI_OY":0,"bagimsiz10_ALDIGI_OY":0,"bagimsiz11_ALDIGI_OY":0,"bagimsiz12_ALDIGI_OY":0,"bagimsiz13_ALDIGI_OY":0,"bagimsiz14_ALDIGI_OY":0,"bagimsiz15_ALDIGI_OY":0,"bagimsiz16_ALDIGI_OY":0,"bagimsiz17_ALDIGI_OY":0,"bagimsiz18_ALDIGI_OY":0,"bagimsiz19_ALDIGI_OY":0,"bagimsiz20_ALDIGI_OY":0,"bagimsiz21_ALDIGI_OY":0,"bagimsiz22_ALDIGI_OY":0,"bagimsiz23_ALDIGI_OY":0,"bagimsiz24_ALDIGI_OY":0,"bagimsiz25_ALDIGI_OY":0,"bagimsiz26_ALDIGI_OY":0,"bagimsiz27_ALDIGI_OY":0,"bagimsiz28_ALDIGI_OY":0,"bagimsiz29_ALDIGI_OY":0,"bagimsiz30_ALDIGI_OY":0,"bagimsiz31_ALDIGI_OY":0,"bagimsiz32_ALDIGI_OY":0,"bagimsiz33_ALDIGI_OY":0,"bagimsiz34_ALDIGI_OY":0,"bagimsiz35_ALDIGI_OY":0,"bagimsiz36_ALDIGI_OY":0,"bagimsiz37_ALDIGI_OY":0,"bagimsiz38_ALDIGI_OY":0,"bagimsiz39_ALDIGI_OY":0,"bagimsiz40_ALDIGI_OY":0,"bagimsiz41_ALDIGI_OY":0,"bagimsiz42_ALDIGI_OY":0,"bagimsiz43_ALDIGI_OY":0,"bagimsiz44_ALDIGI_OY":0,"bagimsiz45_ALDIGI_OY":0,"bagimsiz46_ALDIGI_OY":0,"bagimsiz47_ALDIGI_OY":0,"bagimsiz48_ALDIGI_OY":0,"bagimsiz49_ALDIGI_OY":0,"bagimsiz50_ALDIGI_OY":0,"ittifak1_ALDIGI_OY":0,"ittifak2_ALDIGI_OY":0,"ittifak3_ALDIGI_OY":0,"ittifak4_ALDIGI_OY":0,"ittifak5_ALDIGI_OY":0,"versiyon":2671,"son_ISLEM_TARIHI":"2014-08-10T17:01:55.000+0000","degisiklik_NEDENI":0,"sandik_SONUC_ID":0,"secim_ID":13340,"secim_TURU":0,"parti1_ALDIGI_OY":0,"parti2_ALDIGI_OY":0,"parti3_ALDIGI_OY":0,"parti4_ALDIGI_OY":0,"parti5_ALDIGI_OY":0,"parti6_ALDIGI_OY":0,"parti7_ALDIGI_OY":0,"parti8_ALDIGI_OY":0,"parti9_ALDIGI_OY":0,"parti10_ALDIGI_OY":0,"parti11_ALDIGI_OY":0,"parti12_ALDIGI_OY":0,"parti13_ALDIGI_OY":0,"parti14_ALDIGI_OY":0,"parti15_ALDIGI_OY":0,"parti16_ALDIGI_OY":0,"parti17_ALDIGI_OY":0,"parti18_ALDIGI_OY":0,"parti19_ALDIGI_OY":0,"parti20_ALDIGI_OY":0,"parti21_ALDIGI_OY":0,"parti22_ALDIGI_OY":0,"parti23_ALDIGI_OY":0,"parti24_ALDIGI_OY":0,"parti25_ALDIGI_OY":0,"parti26_ALDIGI_OY":0,"parti27_ALDIGI_OY":0,"parti28_ALDIGI_OY":0,"parti29_ALDIGI_OY":0,"parti30_ALDIGI_OY":0,"bagimsiz1_ALDIGI_OY":67320,"bagimsiz2_ALDIGI_OY":7731,"sandik_ID":0,"secmen_SAYISI":189951,"oy_KULLANAN_SECMEN_SAYISI":156628,"itirazli_GECERLI_OY_SAYISI":0,"gecerli_OY_TOPLAMI":153960,"gecersiz_OY_TOPLAMI":2668,"itirazsiz_GECERLI_OY_SAYISI":153960},{"dis_TEMSILCILIK_ID":0,"birim_ID":0,"ilce_ID":764,"ilce_ADI":"PAMUKKALE","belde_ID":0,"il_ID":20,"il_ADI":"DENİZLİ","ulke_ID":0,"muhtarlik_ID":0,"muhtarlik_ADI":null,"cezaevi_ID":0,"sandik_NO":null,"sandik_SONUC_TUTANAGI":0,"sandik_DOKUM_CETVELI":0,"denetim_TUTANAGI":0,"bagimsiz_TOPLAM_OY":176817,"gumruk_ID":0,"sandik_RUMUZ":null,"gumruk_SANDIK_TARIHI":null,"birlestirme_TUTANAGI_KURUL":0,"birlestirme_TUTANAGI_ULKE":0,"birlestirme_TUTANAGI_ILCE":0,"birlestirme_TUTANAGI_IL":0,"birlestirme_TUTANAGI_DIS_TEMSILCILIK":0,"birlestirme_TUTANAGI_GUMRUK_ILCE":0,"birlestirme_TUTANAGI_GUMRUK_RUMUZ":0,"birlestirme_TUTANAGI_GUMRUK_KURUL":0,"birlestirme_TUTANAGI_TUMDUNYA":0,"birlestirme_TUTANAGI_ULKELER":0,"birlestirme_TUTANAGI_GUMRUKLER":0,"bagimsiz3_ALDIGI_OY":89018,"bagimsiz4_ALDIGI_OY":0,"bagimsiz5_ALDIGI_OY":0,"bagimsiz6_ALDIGI_OY":0,"bagimsiz7_ALDIGI_OY":0,"bagimsiz8_ALDIGI_OY":0,"bagimsiz9_ALDIGI_OY":0,"bagimsiz10_ALDIGI_OY":0,"bagimsiz11_ALDIGI_OY":0,"bagimsiz12_ALDIGI_OY":0,"bagimsiz13_ALDIGI_OY":0,"bagimsiz14_ALDIGI_OY":0,"bagimsiz15_ALDIGI_OY":0,"bagimsiz16_ALDIGI_OY":0,"bagimsiz17_ALDIGI_OY":0,"bagimsiz18_ALDIGI_OY":0,"bagimsiz19_ALDIGI_OY":0,"bagimsiz20_ALDIGI_OY":0,"bagimsiz21_ALDIGI_OY":0,"bagimsiz22_ALDIGI_OY":0,"bagimsiz23_ALDIGI_OY":0,"bagimsiz24_ALDIGI_OY":0,"bagimsiz25_ALDIGI_OY":0,"bagimsiz26_ALDIGI_OY":0,"bagimsiz27_ALDIGI_OY":0,"bagimsiz28_ALDIGI_OY":0,"bagimsiz29_ALDIGI_OY":0,"bagimsiz30_ALDIGI_OY":0,"bagimsiz31_ALDIGI_OY":0,"bagimsiz32_ALDIGI_OY":0,"bagimsiz33_ALDIGI_OY":0,"bagimsiz34_ALDIGI_OY":0,"bagimsiz35_ALDIGI_OY":0,"bagimsiz36_ALDIGI_OY":0,"bagimsiz37_ALDIGI_OY":0,"bagimsiz38_ALDIGI_OY":0,"bagimsiz39_ALDIGI_OY":0,"bagimsiz40_ALDIGI_OY":0,"bagimsiz41_ALDIGI_OY":0,"bagimsiz42_ALDIGI_OY":0,"bagimsiz43_ALDIGI_OY":0,"bagimsiz44_ALDIGI_OY":0,"bagimsiz45_ALDIGI_OY":0,"bagimsiz46_ALDIGI_OY":0,"bagimsiz47_ALDIGI_OY":0,"bagimsiz48_ALDIGI_OY":0,"bagimsiz49_ALDIGI_OY":0,"bagimsiz50_ALDIGI_OY":0,"ittifak1_ALDIGI_OY":0,"ittifak2_ALDIGI_OY":0,"ittifak3_ALDIGI_OY":0,"ittifak4_ALDIGI_OY":0,"ittifak5_ALDIGI_OY":0,"versiyon":2671,"son_ISLEM_TARIHI":"2014-08-10T17:44:04.000+0000","degisiklik_NEDENI":1,"sandik_SONUC_ID":0,"secim_ID":13340,"secim_TURU":0,"parti1_ALDIGI_OY":0,"parti2_ALDIGI_OY":0,"parti3_ALDIGI_OY":0,"parti4_ALDIGI_OY":0,"parti5_ALDIGI_OY":0,"parti6_ALDIGI_OY":0,"parti7_ALDIGI_OY":0,"parti8_ALDIGI_OY":0,"parti9_ALDIGI_OY":0,"parti10_ALDIGI_OY":0,"parti11_ALDIGI_OY":0,"parti12_ALDIGI_OY":0,"parti13_ALDIGI_OY":0,"parti14_ALDIGI_OY":0,"parti15_ALDIGI_OY":0,"parti16_ALDIGI_OY":0,"parti17_ALDIGI_OY":0,"parti18_ALDIGI_OY":0,"parti19_ALDIGI_OY":0,"parti20_ALDIGI_OY":0,"parti21_ALDIGI_OY":0,"parti22_ALDIGI_OY":0,"parti23_ALDIGI_OY":0,"parti24_ALDIGI_OY":0,"parti25_ALDIGI_OY":0,"parti26_ALDIGI_OY":0,"parti27_ALDIGI_OY":0,"parti28_ALDIGI_OY":0,"parti29_ALDIGI_OY":0,"parti30_ALDIGI_OY":0,"bagimsiz1_ALDIGI_OY":82675,"bagimsiz2_ALDIGI_OY":5124,"sandik_ID":0,"secmen_SAYISI":220580,"oy_KULLANAN_SECMEN_SAYISI":180289,"itirazli_GECERLI_OY_SAYISI":607,"gecerli_OY_TOPLAMI":176817,"gecersiz_OY_TOPLAMI":3472,"itirazsiz_GECERLI_OY_SAYISI":176210},{"dis_TEMSILCILIK_ID":0,"birim_ID":0,"ilce_ID":490,"ilce_ADI":"SARAYKÖY","belde_ID":0,"il_ID":20,"il_ADI":"DENİZLİ","ulke_ID":0,"muhtarlik_ID":0,"muhtarlik_ADI":null,"cezaevi_ID":0,"sandik_NO":null,"sandik_SONUC_TUTANAGI":0,"sandik_DOKUM_CETVELI":0,"denetim_TUTANAGI":0,"bagimsiz_TOPLAM_OY":18475,"gumruk_ID":0,"sandik_RUMUZ":null,"gumruk_SANDIK_TARIHI":null,"birlestirme_TUTANAGI_KURUL":0,"birlestirme_TUTANAGI_ULKE":0,"birlestirme_TUTANAGI_ILCE":0,"birlestirme_TUTANAGI_IL":0,"birlestirme_TUTANAGI_DIS_TEMSILCILIK":0,"birlestirme_TUTANAGI_GUMRUK_ILCE":0,"birlestirme_TUTANAGI_GUMRUK_RUMUZ":0,"birlestirme_TUTANAGI_GUMRUK_KURUL":0,"birlestirme_TUTANAGI_TUMDUNYA":0,"birlestirme_TUTANAGI_ULKELER":0,"birlestirme_TUTANAGI_GUMRUKLER":0,"bagimsiz3_ALDIGI_OY":10592,"bagimsiz4_ALDIGI_OY":0,"bagimsiz5_ALDIGI_OY":0,"bagimsiz6_ALDIGI_OY":0,"bagimsiz7_ALDIGI_OY":0,"bagimsiz8_ALDIGI_OY":0,"bagimsiz9_ALDIGI_OY":0,"bagimsiz10_ALDIGI_OY":0,"bagimsiz11_ALDIGI_OY":0,"bagimsiz12_ALDIGI_OY":0,"bagimsiz13_ALDIGI_OY":0,"bagimsiz14_ALDIGI_OY":0,"bagimsiz15_ALDIGI_OY":0,"bagimsiz16_ALDIGI_OY":0,"bagimsiz17_ALDIGI_OY":0,"bagimsiz18_ALDIGI_OY":0,"bagimsiz19_ALDIGI_OY":0,"bagimsiz20_ALDIGI_OY":0,"bagimsiz21_ALDIGI_OY":0,"bagimsiz22_ALDIGI_OY":0,"bagimsiz23_ALDIGI_OY":0,"bagimsiz24_ALDIGI_OY":0,"bagimsiz25_ALDIGI_OY":0,"bagimsiz26_ALDIGI_OY":0,"bagimsiz27_ALDIGI_OY":0,"bagimsiz28_ALDIGI_OY":0,"bagimsiz29_ALDIGI_OY":0,"bagimsiz30_ALDIGI_OY":0,"bagimsiz31_ALDIGI_OY":0,"bagimsiz32_ALDIGI_OY":0,"bagimsiz33_ALDIGI_OY":0,"bagimsiz34_ALDIGI_OY":0,"bagimsiz35_ALDIGI_OY":0,"bagimsiz36_ALDIGI_OY":0,"bagimsiz37_ALDIGI_OY":0,"bagimsiz38_ALDIGI_OY":0,"bagimsiz39_ALDIGI_OY":0,"bagimsiz40_ALDIGI_OY":0,"bagimsiz41_ALDIGI_OY":0,"bagimsiz42_ALDIGI_OY":0,"bagimsiz43_ALDIGI_OY":0,"bagimsiz44_ALDIGI_OY":0,"bagimsiz45_ALDIGI_OY":0,"bagimsiz46_ALDIGI_OY":0,"bagimsiz47_ALDIGI_OY":0,"bagimsiz48_ALDIGI_OY":0,"bagimsiz49_ALDIGI_OY":0,"bagimsiz50_ALDIGI_OY":0,"ittifak1_ALDIGI_OY":0,"ittifak2_ALDIGI_OY":0,"ittifak3_ALDIGI_OY":0,"ittifak4_ALDIGI_OY":0,"ittifak5_ALDIGI_OY":0,"versiyon":2671,"son_ISLEM_TARIHI":"2014-08-10T17:33:46.000+0000","degisiklik_NEDENI":1,"sandik_SONUC_ID":0,"secim_ID":13340,"secim_TURU":0,"parti1_ALDIGI_OY":0,"parti2_ALDIGI_OY":0,"parti3_ALDIGI_OY":0,"parti4_ALDIGI_OY":0,"parti5_ALDIGI_OY":0,"parti6_ALDIGI_OY":0,"parti7_ALDIGI_OY":0,"parti8_ALDIGI_OY":0,"parti9_ALDIGI_OY":0,"parti10_ALDIGI_OY":0,"parti11_ALDIGI_OY":0,"parti12_ALDIGI_OY":0,"parti13_ALDIGI_OY":0,"parti14_ALDIGI_OY":0,"parti15_ALDIGI_OY":0,"parti16_ALDIGI_OY":0,"parti17_ALDIGI_OY":0,"parti18_ALDIGI_OY":0,"parti19_ALDIGI_OY":0,"parti20_ALDIGI_OY":0,"parti21_ALDIGI_OY":0,"parti22_ALDIGI_OY":0,"parti23_ALDIGI_OY":0,"parti24_ALDIGI_OY":0,"parti25_ALDIGI_OY":0,"parti26_ALDIGI_OY":0,"parti27_ALDIGI_OY":0,"parti28_ALDIGI_OY":0,"parti29_ALDIGI_OY":0,"parti30_ALDIGI_OY":0,"bagimsiz1_ALDIGI_OY":6642,"bagimsiz2_ALDIGI_OY":1241,"sandik_ID":0,"secmen_SAYISI":22049,"oy_KULLANAN_SECMEN_SAYISI":18897,"itirazli_GECERLI_OY_SAYISI":0,"gecerli_OY_TOPLAMI":18475,"gecersiz_OY_TOPLAMI":422,"itirazsiz_GECERLI_OY_SAYISI":18475},{"dis_TEMSILCILIK_ID":0,"birim_ID":0,"ilce_ID":733,"ilce_ADI":"SERİNHİSAR","belde_ID":0,"il_ID":20,"il_ADI":"DENİZLİ","ulke_ID":0,"muhtarlik_ID":0,"muhtarlik_ADI":null,"cezaevi_ID":0,"sandik_NO":null,"sandik_SONUC_TUTANAGI":0,"sandik_DOKUM_CETVELI":0,"denetim_TUTANAGI":0,"bagimsiz_TOPLAM_OY":9343,"gumruk_ID":0,"sandik_RUMUZ":null,"gumruk_SANDIK_TARIHI":null,"birlestirme_TUTANAGI_KURUL":0,"birlestirme_TUTANAGI_ULKE":0,"birlestirme_TUTANAGI_ILCE":0,"birlestirme_TUTANAGI_IL":0,"birlestirme_TUTANAGI_DIS_TEMSILCILIK":0,"birlestirme_TUTANAGI_GUMRUK_ILCE":0,"birlestirme_TUTANAGI_GUMRUK_RUMUZ":0,"birlestirme_TUTANAGI_GUMRUK_KURUL":0,"birlestirme_TUTANAGI_TUMDUNYA":0,"birlestirme_TUTANAGI_ULKELER":0,"birlestirme_TUTANAGI_GUMRUKLER":0,"bagimsiz3_ALDIGI_OY":4403,"bagimsiz4_ALDIGI_OY":0,"bagimsiz5_ALDIGI_OY":0,"bagimsiz6_ALDIGI_OY":0,"bagimsiz7_ALDIGI_OY":0,"bagimsiz8_ALDIGI_OY":0,"bagimsiz9_ALDIGI_OY":0,"bagimsiz10_ALDIGI_OY":0,"bagimsiz11_ALDIGI_OY":0,"bagimsiz12_ALDIGI_OY":0,"bagimsiz13_ALDIGI_OY":0,"bagimsiz14_ALDIGI_OY":0,"bagimsiz15_ALDIGI_OY":0,"bagimsiz16_ALDIGI_OY":0,"bagimsiz17_ALDIGI_OY":0,"bagimsiz18_ALDIGI_OY":0,"bagimsiz19_ALDIGI_OY":0,"bagimsiz20_ALDIGI_OY":0,"bagimsiz21_ALDIGI_OY":0,"bagimsiz22_ALDIGI_OY":0,"bagimsiz23_ALDIGI_OY":0,"bagimsiz24_ALDIGI_OY":0,"bagimsiz25_ALDIGI_OY":0,"bagimsiz26_ALDIGI_OY":0,"bagimsiz27_ALDIGI_OY":0,"bagimsiz28_ALDIGI_OY":0,"bagimsiz29_ALDIGI_OY":0,"bagimsiz30_ALDIGI_OY":0,"bagimsiz31_ALDIGI_OY":0,"bagimsiz32_ALDIGI_OY":0,"bagimsiz33_ALDIGI_OY":0,"bagimsiz34_ALDIGI_OY":0,"bagimsiz35_ALDIGI_OY":0,"bagimsiz36_ALDIGI_OY":0,"bagimsiz37_ALDIGI_OY":0,"bagimsiz38_ALDIGI_OY":0,"bagimsiz39_ALDIGI_OY":0,"bagimsiz40_ALDIGI_OY":0,"bagimsiz41_ALDIGI_OY":0,"bagimsiz42_ALDIGI_OY":0,"bagimsiz43_ALDIGI_OY":0,"bagimsiz44_ALDIGI_OY":0,"bagimsiz45_ALDIGI_OY":0,"bagimsiz46_ALDIGI_OY":0,"bagimsiz47_ALDIGI_OY":0,"bagimsiz48_ALDIGI_OY":0,"bagimsiz49_ALDIGI_OY":0,"bagimsiz50_ALDIGI_OY":0,"ittifak1_ALDIGI_OY":0,"ittifak2_ALDIGI_OY":0,"ittifak3_ALDIGI_OY":0,"ittifak4_ALDIGI_OY":0,"ittifak5_ALDIGI_OY":0,"versiyon":2671,"son_ISLEM_TARIHI":"2014-08-10T16:50:33.000+0000","degisiklik_NEDENI":0,"sandik_SONUC_ID":0,"secim_ID":13340,"secim_TURU":0,"parti1_ALDIGI_OY":0,"parti2_ALDIGI_OY":0,"parti3_ALDIGI_OY":0,"parti4_ALDIGI_OY":0,"parti5_ALDIGI_OY":0,"parti6_ALDIGI_OY":0,"parti7_ALDIGI_OY":0,"parti8_ALDIGI_OY":0,"parti9_ALDIGI_OY":0,"parti10_ALDIGI_OY":0,"parti11_ALDIGI_OY":0,"parti12_ALDIGI_OY":0,"parti13_ALDIGI_OY":0,"parti14_ALDIGI_OY":0,"parti15_ALDIGI_OY":0,"parti16_ALDIGI_OY":0,"parti17_ALDIGI_OY":0,"parti18_ALDIGI_OY":0,"parti19_ALDIGI_OY":0,"parti20_ALDIGI_OY":0,"parti21_ALDIGI_OY":0,"parti22_ALDIGI_OY":0,"parti23_ALDIGI_OY":0,"parti24_ALDIGI_OY":0,"parti25_ALDIGI_OY":0,"parti26_ALDIGI_OY":0,"parti27_ALDIGI_OY":0,"parti28_ALDIGI_OY":0,"parti29_ALDIGI_OY":0,"parti30_ALDIGI_OY":0,"bagimsiz1_ALDIGI_OY":4813,"bagimsiz2_ALDIGI_OY":127,"sandik_ID":0,"secmen_SAYISI":11066,"oy_KULLANAN_SECMEN_SAYISI":9604,"itirazli_GECERLI_OY_SAYISI":0,"gecerli_OY_TOPLAMI":9343,"gecersiz_OY_TOPLAMI":261,"itirazsiz_GECERLI_OY_SAYISI":9343},{"dis_TEMSILCILIK_ID":0,"birim_ID":0,"ilce_ID":563,"ilce_ADI":"TAVAS","belde_ID":0,"il_ID":20,"il_ADI":"DENİZLİ","ulke_ID":0,"muhtarlik_ID":0,"muhtarlik_ADI":null,"cezaevi_ID":0,"sandik_NO":null,"sandik_SONUC_TUTANAGI":0,"sandik_DOKUM_CETVELI":0,"denetim_TUTANAGI":0,"bagimsiz_TOPLAM_OY":29711,"gumruk_ID":0,"sandik_RUMUZ":null,"gumruk_SANDIK_TARIHI":null,"birlestirme_TUTANAGI_KURUL":0,"birlestirme_TUTANAGI_ULKE":0,"birlestirme_TUTANAGI_ILCE":0,"birlestirme_TUTANAGI_IL":0,"birlestirme_TUTANAGI_DIS_TEMSILCILIK":0,"birlestirme_TUTANAGI_GUMRUK_ILCE":0,"birlestirme_TUTANAGI_GUMRUK_RUMUZ":0,"birlestirme_TUTANAGI_GUMRUK_KURUL":0,"birlestirme_TUTANAGI_TUMDUNYA":0,"birlestirme_TUTANAGI_ULKELER":0,"birlestirme_TUTANAGI_GUMRUKLER":0,"bagimsiz3_ALDIGI_OY":12819,"bagimsiz4_ALDIGI_OY":0,"bagimsiz5_ALDIGI_OY":0,"bagimsiz6_ALDIGI_OY":0,"bagimsiz7_ALDIGI_OY":0,"bagimsiz8_ALDIGI_OY":0,"bagimsiz9_ALDIGI_OY":0,"bagimsiz10_ALDIGI_OY":0,"bagimsiz11_ALDIGI_OY":0,"bagimsiz12_ALDIGI_OY":0,"bagimsiz13_ALDIGI_OY":0,"bagimsiz14_ALDIGI_OY":0,"bagimsiz15_ALDIGI_OY":0,"bagimsiz16_ALDIGI_OY":0,"bagimsiz17_ALDIGI_OY":0,"bagimsiz18_ALDIGI_OY":0,"bagimsiz19_ALDIGI_OY":0,"bagimsiz20_ALDIGI_OY":0,"bagimsiz21_ALDIGI_OY":0,"bagimsiz22_ALDIGI_OY":0,"bagimsiz23_ALDIGI_OY":0,"bagimsiz24_ALDIGI_OY":0,"bagimsiz25_ALDIGI_OY":0,"bagimsiz26_ALDIGI_OY":0,"bagimsiz27_ALDIGI_OY":0,"bagimsiz28_ALDIGI_OY":0,"bagimsiz29_ALDIGI_OY":0,"bagimsiz30_ALDIGI_OY":0,"bagimsiz31_ALDIGI_OY":0,"bagimsiz32_ALDIGI_OY":0,"bagimsiz33_ALDIGI_OY":0,"bagimsiz34_ALDIGI_OY":0,"bagimsiz35_ALDIGI_OY":0,"bagimsiz36_ALDIGI_OY":0,"bagimsiz37_ALDIGI_OY":0,"bagimsiz38_ALDIGI_OY":0,"bagimsiz39_ALDIGI_OY":0,"bagimsiz40_ALDIGI_OY":0,"bagimsiz41_ALDIGI_OY":0,"bagimsiz42_ALDIGI_OY":0,"bagimsiz43_ALDIGI_OY":0,"bagimsiz44_ALDIGI_OY":0,"bagimsiz45_ALDIGI_OY":0,"bagimsiz46_ALDIGI_OY":0,"bagimsiz47_ALDIGI_OY":0,"bagimsiz48_ALDIGI_OY":0,"bagimsiz49_ALDIGI_OY":0,"bagimsiz50_ALDIGI_OY":0,"ittifak1_ALDIGI_OY":0,"ittifak2_ALDIGI_OY":0,"ittifak3_ALDIGI_OY":0,"ittifak4_ALDIGI_OY":0,"ittifak5_ALDIGI_OY":0,"versiyon":2671,"son_ISLEM_TARIHI":"2014-08-13T06:02:43.000+0000","degisiklik_NEDENI":2,"sandik_SONUC_ID":0,"secim_ID":13340,"secim_TURU":0,"parti1_ALDIGI_OY":0,"parti2_ALDIGI_OY":0,"parti3_ALDIGI_OY":0,"parti4_ALDIGI_OY":0,"parti5_ALDIGI_OY":0,"parti6_ALDIGI_OY":0,"parti7_ALDIGI_OY":0,"parti8_ALDIGI_OY":0,"parti9_ALDIGI_OY":0,"parti10_ALDIGI_OY":0,"parti11_ALDIGI_OY":0,"parti12_ALDIGI_OY":0,"parti13_ALDIGI_OY":0,"parti14_ALDIGI_OY":0,"parti15_ALDIGI_OY":0,"parti16_ALDIGI_OY":0,"parti17_ALDIGI_OY":0,"parti18_ALDIGI_OY":0,"parti19_ALDIGI_OY":0,"parti20_ALDIGI_OY":0,"parti21_ALDIGI_OY":0,"parti22_ALDIGI_OY":0,"parti23_ALDIGI_OY":0,"parti24_ALDIGI_OY":0,"parti25_ALDIGI_OY":0,"parti26_ALDIGI_OY":0,"parti27_ALDIGI_OY":0,"parti28_ALDIGI_OY":0,"parti29_ALDIGI_OY":0,"parti30_ALDIGI_OY":0,"bagimsiz1_ALDIGI_OY":16469,"bagimsiz2_ALDIGI_OY":423,"sandik_ID":0,"secmen_SAYISI":36530,"oy_KULLANAN_SECMEN_SAYISI":30580,"itirazli_GECERLI_OY_SAYISI":2,"gecerli_OY_TOPLAMI":29711,"gecersiz_OY_TOPLAMI":869,"itirazsiz_GECERLI_OY_SAYISI":29709}]