[{"ilId":1,"ilceId":650,"ilAdi":"ADANA","ilceAdi":"ALADAĞ","rteoy":6043,"sdoy":207,"emioy":4078,"secmenSayisi":12762,"gecersizOyToplami":284,"itirazsizGecerliOySayisi":10328,"gecerliOyToplami":10328,"itirazliGecerliOySayisi":0,"secimId":13340,"oyKullananSecmenSayisi":10612,"sonIslemTarihi":"2014-08-10T16:53:35.000+0000"}, {"ilId":1,"ilceId":117,"ilAdi":"ADANA","ilceAdi":"CEYHAN","rteoy":29985,"sdoy":11159,"emioy":39661,"secmenSayisi":107433,"gecersizOyToplami":1140,"itirazsizGecerliOySayisi":80805,"gecerliOyToplami":80805,"itirazliGecerliOySayisi":0,"secimId":13340,"oyKullananSecmenSayisi":81945,"sonIslemTarihi":"2014-08-10T16:42:57.000+0000"}, {"ilId":1,"ilceId":982,"ilAdi":"ADANA","ilceAdi":"ÇUKUROVA","rteoy":52848,"sdoy":8021,"emioy":127167,"secmenSayisi":249778,"gecersizOyToplami":1986,"itirazsizGecerliOySayisi":188034,"gecerliOyToplami":188036,"itirazliGecerliOySayisi":2,"secimId":13340,"oyKullananSecmenSayisi":190022,"sonIslemTarihi":"2014-08-10T17:31:59.000+0000"}, {"ilId":1,"ilceId":227,"ilAdi":"ADANA","ilceAdi":"FEKE","rteoy":5891,"sdoy":232,"emioy":3831,"secmenSayisi":13220,"gecersizOyToplami":271,"itirazsizGecerliOySayisi":9954,"gecerliOyToplami":9954,"itirazliGecerliOySayisi":0,"secimId":13340,"oyKullananSecmenSayisi":10225,"sonIslemTarihi":"2014-08-10T18:12:45.000+0000"}, {"ilId":1,"ilceId":699,"ilAdi":"ADANA","ilceAdi":"İMAMOĞLU","rteoy":7925,"sdoy":314,"emioy":6287,"secmenSayisi":20017,"gecersizOyToplami":273,"itirazsizGecerliOySayisi":14525,"gecerliOyToplami":14526,"itirazliGecerliOySayisi":1,"secimId":13340,"oyKullananSecmenSayisi":14799,"sonIslemTarihi":"2014-08-10T16:59:56.000+0000"}, {"ilId":1,"ilceId":332,"ilAdi":"ADANA","ilceAdi":"KARAİSALI","rteoy":8531,"sdoy":157,"emioy":4443,"secmenSayisi":15893,"gecersizOyToplami":259,"itirazsizGecerliOySayisi":13131,"gecerliOyToplami":13131,"itirazliGecerliOySayisi":0,"secimId":13340,"oyKullananSecmenSayisi":13390,"sonIslemTarihi":"2014-08-10T17:11:12.000+0000"}, {"ilId":1,"ilceId":338,"ilAdi":"ADANA","ilceAdi":"KARATAŞ","rteoy":3579,"sdoy":572,"emioy":8346,"secmenSayisi":15880,"gecersizOyToplami":153,"itirazsizGecerliOySayisi":12497,"gecerliOyToplami":12497,"itirazliGecerliOySayisi":0,"secimId":13340,"oyKullananSecmenSayisi":12650,"sonIslemTarihi":"2014-08-10T16:38:59.000+0000"}, {"ilId":1,"ilceId":379,"ilAdi":"ADANA","ilceAdi":"KOZAN","rteoy":32818,"sdoy":1045,"emioy":30841,"secmenSayisi":88427,"gecersizOyToplami":1247,"itirazsizGecerliOySayisi":64704,"gecerliOyToplami":64704,"itirazliGecerliOySayisi":0,"secimId":13340,"oyKullananSecmenSayisi":65951,"sonIslemTarihi":"2014-08-10T18:18:38.000+0000"}, {"ilId":1,"ilceId":473,"ilAdi":"ADANA","ilceAdi":"POZANTI","rteoy":6714,"sdoy":237,"emioy":5582,"secmenSayisi":15414,"gecersizOyToplami":254,"itirazsizGecerliOySayisi":12533,"gecerliOyToplami":12533,"itirazliGecerliOySayisi":0,"secimId":13340,"oyKullananSecmenSayisi":12787,"sonIslemTarihi":"2014-08-10T16:37:26.000+0000"}, {"ilId":1,"ilceId":481,"ilAdi":"ADANA","ilceAdi":"SAİMBEYLİ","rteoy":4929,"sdoy":159,"emioy":2890,"secmenSayisi":11346,"gecersizOyToplami":182,"itirazsizGecerliOySayisi":7978,"gecerliOyToplami":7978,"itirazliGecerliOySayisi":0,"secimId":13340,"oyKullananSecmenSayisi":8160,"sonIslemTarihi":"2014-08-10T17:00:21.000+0000"}, {"ilId":1,"ilceId":981,"ilAdi":"ADANA","ilceAdi":"SARIÇAM","rteoy":31212,"sdoy":2514,"emioy":34258,"secmenSayisi":88588,"gecersizOyToplami":1048,"itirazsizGecerliOySayisi":67984,"gecerliOyToplami":67984,"itirazliGecerliOySayisi":0,"secimId":13340,"oyKullananSecmenSayisi":69032,"sonIslemTarihi":"2014-08-10T17:24:08.000+0000"}, {"ilId":1,"ilceId":4,"ilAdi":"ADANA","ilceAdi":"SEYHAN","rteoy":130686,"sdoy":62954,"emioy":183639,"secmenSayisi":518573,"gecersizOyToplami":4645,"itirazsizGecerliOySayisi":377091,"gecerliOyToplami":377279,"itirazliGecerliOySayisi":188,"secimId":13340,"oyKullananSecmenSayisi":381924,"sonIslemTarihi":"2014-08-10T18:12:22.000+0000"}, {"ilId":1,"ilceId":580,"ilAdi":"ADANA","ilceAdi":"TUFANBEYLİ","rteoy":4859,"sdoy":167,"emioy":5205,"secmenSayisi":13427,"gecersizOyToplami":189,"itirazsizGecerliOySayisi":10227,"gecerliOyToplami":10231,"itirazliGecerliOySayisi":4,"secimId":13340,"oyKullananSecmenSayisi":10420,"sonIslemTarihi":"2014-08-10T16:26:06.000+0000"}, {"ilId":1,"ilceId":627,"ilAdi":"ADANA","ilceAdi":"YUMURTALIK","rteoy":4032,"sdoy":146,"emioy":6176,"secmenSayisi":13362,"gecersizOyToplami":169,"itirazsizGecerliOySayisi":10354,"gecerliOyToplami":10354,"itirazliGecerliOySayisi":0,"secimId":13340,"oyKullananSecmenSayisi":10523,"sonIslemTarihi":"2014-08-10T17:18:51.000+0000"}, {"ilId":1,"ilceId":641,"ilAdi":"ADANA","ilceAdi":"YÜREĞİR","rteoy":87840,"sdoy":26646,"emioy":79163,"secmenSayisi":268497,"gecersizOyToplami":2854,"itirazsizGecerliOySayisi":193646,"gecerliOyToplami":193649,"itirazliGecerliOySayisi":3,"secimId":13340,"oyKullananSecmenSayisi":196503,"sonIslemTarihi":"2014-08-10T18:20:00.000+0000"}]