[{"ilId":69,"ilceId":660,"ilAdi":"BAYBURT","ilceAdi":"AYDINTEPE","rteoy":3494,"sdoy":26,"emioy":808,"secmenSayisi":5219,"gecersizOyToplami":102,"itirazsizGecerliOySayisi":4328,"gecerliOyToplami":4328,"itirazliGecerliOySayisi":0,"secimId":13340,"oyKullananSecmenSayisi":4430,"sonIslemTarihi":"2014-08-10T16:23:29.000+0000"}, {"ilId":69,"ilceId":75,"ilAdi":"BAYBURT","ilceAdi":"BAYBURT MERKEZ","rteoy":26122,"sdoy":255,"emioy":6467,"secmenSayisi":43364,"gecersizOyToplami":621,"itirazsizGecerliOySayisi":32844,"gecerliOyToplami":32844,"itirazliGecerliOySayisi":0,"secimId":13340,"oyKullananSecmenSayisi":33465,"sonIslemTarihi":"2014-08-10T17:06:54.000+0000"}, {"ilId":69,"ilceId":681,"ilAdi":"BAYBURT","ilceAdi":"DEMİRÖZÜ","rteoy":4501,"sdoy":38,"emioy":831,"secmenSayisi":6156,"gecersizOyToplami":64,"itirazsizGecerliOySayisi":5370,"gecerliOyToplami":5370,"itirazliGecerliOySayisi":0,"secimId":13340,"oyKullananSecmenSayisi":5434,"sonIslemTarihi":"2014-08-10T17:26:01.000+0000"}]